Workbook

Sheet Cham_diem
A1: STT | B1: Nguon_ZH | C1: Tham_chieu_VI | D1: Ban_dich_He_A | E1: Ban_dich_He_B | F1: Nguoi_cham_chinh | G1: Diem_A_chinh | H1: Diem_B_chinh | I1: Nguoi_cham_cheo | J1: Diem_A_cheo | K1: Diem_B_cheo | L1: Ghi_chu_A (chính+chéo) | M1: Ghi_chu_B (chính+chéo) | N1: Ghi_chu_chung | O1: Diem_A_final | P1: Diem_B_final | Q1: Ket_luan_AI | R1: Ghi_chu_bo_sung
A2: 1 | B2: =Du_lieu_goc!C3 -> 在遭受新冠肺炎疫情不小影响的背景下，2022年对越南恢复和发展经济具有重要意义。 | C2: =Du_lieu_goc!D3 -> Năm 2022 là năm có ý nghĩa quan trọng trong phục hồi và phát triển kinh tế Việt Nam sau những tác động của dịch COVID - 19. | D2: Trong bối cảnh chịu ảnh hưởng không nhỏ từ đại dịch COVID-19, năm 2022 có ý nghĩa quan trọng đối với sự phục hồi và phát triển kinh tế của Việt Nam. | E2: Trong bối cảnh ảnh hưởng nặng nề của dịch bệnh Covid-19, năm 2022 có ý nghĩa rất lớn đối với sự phục hồi và phát triển kinh tế của Việt Nam. | F2: Người 1 | G2: 95 | H2: 90 | I2: Người 2 | J2: 90 | K2: 78 | O2: 92 | P2: 84 | Q2: Hai người chấm lệch nhẹ (12 điểm).
A3: 2 | B3: =Du_lieu_goc!C4 -> 与新冠肺炎病毒共处不仅是医疗卫生问题，而且还涉及国家经济及社会所有活动的运作方式。 | C3: =Du_lieu_goc!D4 -> Sống chung với dịch COVID-19 không chỉ là vấn đề về y tế mà còn liên quan tới cả cách thức vận hành nền kinh tế và mọi hoạt động của xã hội. | D3: Việc chung sống với virus SARS-CoV-2 không chỉ là vấn đề y tế công cộng mà còn liên quan đến cách thức vận hành của nền kinh tế quốc gia và mọi hoạt động xã hội. | E3: Sống chung với Covid-19 không chỉ là vấn đề y tế, sức khỏe mà còn liên quan đến cách thức vận hành của mọi hoạt động kinh tế, xã hội của đất nước. | F3: Người 1 | G3: 90 | H3: 88 | I3: Người 2 | J3: 90 | K3: 84 | O3: 90 | P3: 86 | Q3: Hai người chấm thống nhất cao.
A4: 3 | B4: =Du_lieu_goc!C5 -> 为使经济尽可能早地恢复并可持续发展，同塔省国会代表黎明欢表示，应考虑经济自主性，制定政策提高经济主动性、抵御力和自主性。 | C4: =Du_lieu_goc!D5 -> Để nền kinh tế phát triển ổn định, sớm phục hồi, đại biểu Lê Minh Hoan, đoàn đại biểu Quốc hội tỉnh Đồng Tháp, cho rằng cần xem xét đến tính tự chủ của nền kinh tế, có chính sách nâng cao sức chủ động, sức chống chịu, tính tự chủ của nền kinh tế. | D4: Để nền kinh tế phục hồi và phát triển bền vững trong thời gian sớm nhất, đại biểu Quốc hội tỉnh Đồng Tháp Lê Minh Hoan cho rằng cần xem xét tính tự chủ của nền kinh tế, xây dựng các chính sách nâng cao tính chủ động, khả năng chống chịu và tự chủ của nền kinh tế. | E4: Để nền kinh tế phục hồi và phát triển bền vững trong thời gian sớm nhất, ông Leong Huân, đại diện Quốc hội tỉnh Đồng Tháp cho rằng, cần xem xét tự chủ kinh tế và xây dựng chính sách nâng cao tính chủ động, tự cường, tự chủ về kinh tế. | F4: Người 1 | G4: 90 | H4: 55 | I4: Người 2 | J4: 90 | K4: 45 | M4: Sai tên Lê Minh Hoan thành “Leong Huân”, làm sai người đưa ra nhận định. | O4: 90 | P4: 50 | Q4: Hai người chấm lệch nhẹ (10 điểm). A vượt B rõ rệt (90 vs 50). Ghi nhận lỗi: B: Sai tên Lê Minh Hoan thành “Leong Huân”, làm sai người đưa ra nhận định. Điểm thấp — nên kiểm tra thủ công trước khi đưa vào tính tương quan.
A5: 4 | B5: =Du_lieu_goc!C6 -> 尽早恢复经济、与病毒安全共处 | C5: =Du_lieu_goc!D6 -> Sớm phục hồi kinh tế, sống chung an toàn với dịch COVID - 19 | D5: Sớm phục hồi kinh tế, chung sống an toàn với virus | E5: Khôi phục nền kinh tế càng sớm càng tốt và chung sống an toàn với virus | F5: Người 1 | G5: 88 | H5: 85 | I5: Người 2 | J5: 96 | K5: 95 | O5: 92 | P5: 90 | Q5: Hai người chấm lệch nhẹ (10 điểm). A và B tương đương (92 vs 90).
A6: 5 | B6: =Du_lieu_goc!C7 -> 此外，进出口还实现了正增长。 | C6: =Du_lieu_goc!D7 -> Ngoài ra, một số tín hiệu về xuất nhập khẩu vẫn tăng trưởng. | D6: Ngoài ra, xuất nhập khẩu cũng đạt mức tăng trưởng dương. | E6: Ngoài ra, xuất nhập khẩu cũng đạt mức tăng trưởng tích cực. | F6: Người 1 | G6: 92 | H6: 88 | I6: Người 2 | J6: 90 | K6: 86 | O6: 91 | P6: 87 | Q6: Hai người chấm thống nhất cao.
A7: 6 | B7: =Du_lieu_goc!C8 -> 国会将就此颁布更详细的新决议。 | C7: =Du_lieu_goc!D8 -> Chắc chắn Quốc hội sẽ ban hành Nghị quyết nói rõ vấn đề này. | D7: Quốc hội sẽ ban hành một nghị quyết chi tiết hơn về vấn đề này. | E7: Quốc hội sẽ ban hành nghị quyết mới chi tiết hơn về vấn đề này. | F7: Người 1 | G7: 92 | H7: 93 | I7: Người 2 | J7: 85 | K7: 88 | M7: [Thắc mắc gốc] mới → [Đối chiếu bản Trung] B có "mới" (khớp 新决议 trong bản Trung), A thiếu — B chính xác hơn ở điểm này. | O7: 88 | P7: 90 | Q7: Hai người chấm lệch nhẹ (7 điểm). A và B tương đương (88 vs 90). Ghi nhận lỗi: A: mới
A8: 7 | B8: =Du_lieu_goc!C9 -> 防疫工作的方针是安全、灵活适应和有效防控，先决条件是提高疫苗覆盖率。 | C8: =Du_lieu_goc!D9 -> Về phòng chống dịch, cần đặt trọng tâm vào chủ trương thích ứng an toàn, linh hoạt và có hiệu quả với dịch bệnh, điều kiện tiên quyết là bao phủ vaccine. | D8: Phương châm công tác phòng chống dịch là an toàn, linh hoạt thích ứng và kiểm soát hiệu quả, điều kiện tiên quyết là nâng cao tỷ lệ bao phủ vắc-xin. | E8: Phương châm của công tác phòng chống dịch bệnh là an toàn, thích ứng linh hoạt, phòng ngừa và kiểm soát hiệu quả, điều kiện tiên quyết là tăng cường độ bao phủ vắc xin. | F8: Người 1 | G8: 93 | H8: 88 | I8: Người 2 | J8: 90 | K8: 88 | M8: [Thắc mắc gốc] phòng ngừa → [Đối chiếu bản Trung] B tách "phòng ngừa và kiểm soát" sát với 防控 hơn; A gộp thành "kiểm soát". | O8: 92 | P8: 88 | Q8: Hai người chấm thống nhất cao. Ghi nhận lỗi: A: phòng ngừa
A9: 8 | B9: =Du_lieu_goc!C10 -> 越南不能一直封闭，要重新开放，以解决就业、收入、经济社会发展等问题。 | C9: =Du_lieu_goc!D10 -> Việt Nam không thể đóng cửa mãi, mà phải mở cửa để giải quyết việc làm, thu nhập, phát triển kinh tế - xã hội. | D9: Việt Nam không thể tiếp tục đóng cửa mà cần mở cửa trở lại để giải quyết các vấn đề về việc làm, thu nhập, phát triển kinh tế - xã hội. | E9: Việt Nam không thể tiếp tục đóng cửa và phải mở cửa trở lại để giải quyết các vấn đề như việc làm, thu nhập và phát triển kinh tế, xã hội. | F9: Người 1 | G9: 93 | H9: 92 | I9: Người 2 | J9: 88 | K9: 91 | N9: [Thắc mắc gốc] mà/và? → [Đối chiếu bản Trung] Khác biệt "mà cần" (A) / "và phải" (B) chỉ là biến thể liên từ, không đổi nghĩa. | O9: 90 | P9: 92 | Q9: Hai người chấm thống nhất cao. A và B tương đương (90 vs 92). Ghi nhận lỗi: A: mà/và?
A10: 9 | B10: =Du_lieu_goc!C11 -> 2021年是越南实施2021-2026年新阶段性别平等战略的第一年。 | C10: =Du_lieu_goc!D11 -> Năm 2021 là năm Việt Nam bắt đầu thực hiện Chiến lược bình đẳng giới của giai đoạn mới (2021- 2026). | D10: Năm 2021 là năm đầu tiên Việt Nam triển khai chiến lược bình đẳng giới giai đoạn mới 2021-2026. | E10: Năm 2021 là năm đầu tiên Việt Nam thực hiện giai đoạn mới của Chiến lược bình đẳng giới 2021-2026. | F10: Người 1 | G10: 93 | H10: 92 | I10: Người 2 | J10: 92 | K10: 84 | N10: [Thắc mắc gốc] nghĩa khác → [Đối chiếu bản Trung] Nghi ngờ khác nghĩa: A/B dùng "năm đầu tiên triển khai", đối chiếu dùng "bắt đầu thực hiện" — tương đương. | O10: 92 | P10: 88 | Q10: Hai người chấm lệch nhẹ (8 điểm). Ghi nhận lỗi: A: nghĩa khác
A11: 10 | B11: =Du_lieu_goc!C12 -> 其他研究也显示，新冠肺炎疫情对女性产生了深远的影响，女性失业率比男性高得多，但仍要肩负在学校停课期间照顾家庭和孩子的重担。 | C11: =Du_lieu_goc!D12 -> Các nghiên cứu khác cũng cho thấy dịch Covid-19 đã tác động sâu sắc đối với phụ nữ, những người có nguy cơ mất việc làm cao hơn nhiều so với nam giới, trong khi vẫn phải đảm nhận gánh nặng trong sóc gia đình, con cái khi các trường học bị đóng cửa. | D11: Các nghiên cứu khác cũng chỉ ra rằng đại dịch COVID-19 đã tác động sâu sắc đến phụ nữ, với tỷ lệ thất nghiệp ở phụ nữ cao hơn đáng kể so với nam giới, trong khi họ vẫn phải gánh vác trách nhiệm chăm sóc gia đình và con cái trong thời gian trường học đóng cửa. | E11: Các nghiên cứu khác chỉ ra rằng đại dịch COVID-19 đã tác động sâu sắc đến phụ nữ, những người đang có tỷ lệ thất nghiệp cao hơn nhiều so với nam giới nhưng vẫn phải gánh gánh nặng chăm sóc gia đình và con cái khi trường học đóng cửa. | F11: Người 1 | G11: 90 | H11: 82 | I11: Người 2 | J11: 82 | K11: 84 | O11: 86 | P11: 83 | Q11: Hai người chấm lệch nhẹ (8 điểm). A và B tương đương (86 vs 83).
A12: 11 | B12: =Du_lieu_goc!C13 -> 特别是对越南来说，2020年以来，越南经历了4波疫情，给社会经济的所有领域造成了严重影响，成为实施性别平等和妇女进步事业乃至性别平等国家战略目标的挑战。 | C12: =Du_lieu_goc!D13 -> Riêng đối với Việt Nam, từ năm 2020 đến nay, Việt Nam đã trải qua 4 đợt bùng phát dịch, tác động nghiêm trọng tới tất cả các lĩnh vực của nền kinh tế - xã hội, gây thách thức cho việc thực hiện bình đẳng giới và vì sự tiến bộ phụ nữ cũng như việc triển khai thực hiện các mục tiêu chiến lược quốc gia về bình đẳng giới. | D12: Đặc biệt đối với Việt Nam, kể từ năm 2020, Việt Nam đã trải qua 4 đợt dịch bệnh, gây ảnh hưởng nghiêm trọng đến mọi lĩnh vực kinh tế - xã hội, trở thành thách thức đối với việc thực hiện mục tiêu bình đẳng giới và tiến bộ của phụ nữ, cũng như các mục tiêu chiến lược quốc gia về bình đẳng giới. | E12: Đặc biệt đối với Việt Nam, kể từ năm 2020, Việt Nam đã trải qua 4 đợt dịch bệnh, tác động nghiêm trọng đến mọi lĩnh vực của kinh tế xã hội và trở thành thách thức thực hiện sự nghiệp bình đẳng giới, vì sự tiến bộ của phụ nữ và thậm chí là mục tiêu chiến lược quốc gia về bình đẳng giới. | F12: Người 1 | G12: 90 | H12: 88 | I12: Người 2 | J12: 87 | K12: 82 | N12: [Thắc mắc gốc] riêng/đặc biệt? → [Đối chiếu bản Trung] Đối chiếu dùng "Riêng đối với", A/B dùng "Đặc biệt đối với". Bản Trung là 特别是 → A/B sát hơn. | O12: 88 | P12: 85 | Q12: Hai người chấm lệch nhẹ (6 điểm). A và B tương đương (88 vs 85). Ghi nhận lỗi: A: riêng/đặc biệt?
A13: 12 | B13: =Du_lieu_goc!C14 -> 越南政府总理范明政10月20日上午在15届国会2次会议开幕式上做2021年经济社会情况及2022年经济社会发展计划草案报告，概述越南各领域取得的重要结果，其中包括新冠疫情防控工作。 | C13: =Du_lieu_goc!D14 -> Báo cáo về tình hình kinh tế - xã hội năm 2021 dự kiến kế hoạch phát triển kinh tế xã hội năm 2022, tại phiên khai mạc kỳ họp thứ 2, Quốc hội khóa XV sáng 20/10, Thủ tướng Phạm Minh Chính khái quát lại những kết quả quan trọng mà Việt Nam đạt được trên các lĩnh vực, trong đó đặc biệt nhấn mạnh đến công tác phòng chống dịch COVID - 19. | D13: Sáng ngày 20 tháng 10, tại lễ khai mạc kỳ họp thứ hai, Quốc hội khóa 15, Thủ tướng Chính phủ Việt Nam Phạm Minh Chính đã trình bày báo cáo về tình hình kinh tế - xã hội năm 2021 và kế hoạch phát triển kinh tế - xã hội năm 2022. Báo cáo đã khái quát những kết quả quan trọng đạt được trên các lĩnh vực của Việt Nam, trong đó có công tác phòng, chống dịch bệnh COVID-19. | E13: Sáng 20/10, Thủ tướng Phạm Minh Chính đã báo cáo về tình hình kinh tế, xã hội năm 2021 và dự thảo kế hoạch phát triển kinh tế, xã hội năm 2022 tại lễ khai mạc kỳ họp thứ hai, Quốc hội lần thứ 15, nêu những kết quả quan trọng đạt được trên nhiều lĩnh vực ở Việt Nam, trong đó có công tác phòng, chống dịch bệnh vương miện mới. | F13: Người 1 | G13: 90 | H13: 45 | I13: Người 2 | J13: 80 | K13: 52 | M13: “Quốc hội khóa XV” bị đổi thành “Quốc hội lần thứ 15” và COVID-19 thành “dịch bệnh vương miện mới”, làm sai thuật ngữ quan trọng. | N13: [Thắc mắc gốc] trong đó đặc biệt? → [Đối chiếu bản Trung] Đối chiếu thêm "đặc biệt nhấn mạnh", bản Trung chỉ có 其中包括 (trong đó bao gồm) → đối chiếu tự thêm sắc thái. | O13: 85 | P13: 48 | Q13: Hai người chấm lệch nhẹ (10 điểm). A vượt B rõ rệt (85 vs 48). Ghi nhận lỗi: A: trong đó đặc biệt? | B: “Quốc hội khóa XV” bị đổi thành “Quốc hội lần thứ 15” và COVID-19 thành “dịch bệnh vương miện mới”, làm sai thuật ngữ quan trọng. Điểm thấp — nên kiểm tra thủ công trước khi đưa vào tính tương quan.
A14: 13 | B14: =Du_lieu_goc!C15 -> 集中复苏经济，维持增长动力 | C14: =Du_lieu_goc!D15 -> Tập trung phục hồi kinh tế, duy trì các động lực tăng trưởng | D14: Tập trung phục hồi kinh tế, duy trì động lực tăng trưởng | E14: Tập trung phục hồi nền kinh tế và duy trì đà tăng trưởng | F14: Người 1 | G14: 93 | H14: 90 | I14: Người 2 | J14: 90 | K14: 82 | O14: 92 | P14: 86 | Q14: Hai người chấm lệch nhẹ (8 điểm).
A15: 14 | B15: =Du_lieu_goc!C16 -> 防疫工作是政府指导、调控工作的优先 | C15: =Du_lieu_goc!D16 -> Công tác phòng, chống dịch COVID-19 là ưu tiên hàng đầu trong chỉ đạo, điều hành | D15: Công tác phòng chống dịch bệnh là ưu tiên hàng đầu trong công tác chỉ đạo và điều tiết của chính phủ. | E15: Công tác phòng chống dịch bệnh là ưu tiên trong hướng dẫn và quy định của chính phủ | F15: Người 1 | G15: 90 | H15: 78 | I15: Người 2 | J15: 82 | K15: 60 | M15: “Chỉ đạo, điều hành” bị đổi thành “hướng dẫn và quy định”, làm lệch vai trò của Chính phủ. | N15: [Thắc mắc gốc] Mất từ COVID → [Đối chiếu bản Trung] Đối chiếu thêm "COVID-19", bản Trung chỉ ghi 防疫工作 (công tác phòng dịch) → đối chiếu tự thêm. | O15: 86 | P15: 69 | Q15: LỆCH LỚN 18 điểm giữa chấm chính và chấm chéo — cần rà lại. A vượt B rõ rệt (86 vs 69). Ghi nhận lỗi: A: Mất từ COVID | B: “Chỉ đạo, điều hành” bị đổi thành “hướng dẫn và quy định”, làm lệch vai trò của Chính phủ.
A16: 15 | B16: =Du_lieu_goc!C17 -> 集中复苏经济，维持增长动力,不让增长动力减弱 | C16: =Du_lieu_goc!D17 -> Tập trung khôi phục kinh tế , duy trì động lực tăng trưởng , không để suy giảm động lực tăng trưởng | D16: Tập trung phục hồi kinh tế, duy trì động lực tăng trưởng, không để động lực tăng trưởng suy yếu. | E16: Tập trung phục hồi nền kinh tế, duy trì đà tăng trưởng, ngăn chặn đà tăng trưởng suy yếu | F16: Người 1 | G16: 90 | H16: 90 | I16: Người 2 | J16: 91 | K16: 84 | N16: [Thắc mắc gốc] B nên thấp hơn A → [Đối chiếu bản Trung] Đề xuất B thấp hơn A: B dùng "ngăn chặn đà tăng trưởng suy yếu" — diễn đạt kém tự nhiên hơn A. | O16: 90 | P16: 87 | Q16: Hai người chấm lệch nhẹ (6 điểm). A và B tương đương (90 vs 87). Ghi nhận lỗi: A: B nên thấp hơn A
A17: 16 | B17: =Du_lieu_goc!C18 -> 范明政强调，今年最后几个月将集中防疫，制定安全、灵活路线图，有效控制疫情，克服疫情后果，恢复、发展经济社会。 | C17: =Du_lieu_goc!D18 -> Thủ tướng Phạm Minh Chính khẳng định trong những tháng cuối năm, sẽ tập trung nỗ lực cao nhất cho phòng, chống dịch COVID-19, có lộ trình thích ứng an toàn, linh hoạt, phấn đấu kiểm soát hiệu quả dịch bệnh trên phạm vi toàn quốc để tập trung khắc phục hậu quả của dịch bệnh và khôi phục, phát triển kinh tế xã hội. | D17: Phạm Minh Chính nhấn mạnh, những tháng cuối năm sẽ tập trung phòng chống dịch bệnh, xây dựng lộ trình an toàn, linh hoạt, kiểm soát hiệu quả dịch bệnh, khắc phục hậu quả dịch bệnh, phục hồi và phát triển kinh tế xã hội. | E17: Fan Mingzheng nhấn mạnh, trong những tháng cuối năm nay, chúng ta sẽ tập trung vào công tác phòng chống dịch bệnh, xây dựng lộ trình an toàn và linh hoạt, kiểm soát dịch bệnh hiệu quả, khắc phục hậu quả của dịch bệnh, khôi phục và phát triển kinh tế, xã hội. | F17: Người 1 | G17: 90 | H17: 40 | I17: =I16 -> Người 2 | J17: 78 | K17: 42 | L17: Bỏ nhiều ý trong tham chiếu như “nỗ lực cao nhất”, “phấn đấu” và “trên phạm vi toàn quốc”, nên mức độ và phạm vi hành động bị giảm. | M17: Sai tên Phạm Minh Chính thành “Fan Mingzheng”; đồng thời cũng bỏ nhiều ý về mức độ và phạm vi hành động. | N17: [Thắc mắc gốc] "Tập trung cao nhất" cả 2 chưa diễn giải được → [Đối chiếu bản Trung] Cả A và B đều chưa diễn đạt được "tập trung cao nhất"; nhưng bản Trung chỉ có 集中 → không phải lỗi của bản dịch. | O17: 84 | P17: 41 | Q17: Hai người chấm lệch nhẹ (12 điểm). A vượt B rõ rệt (84 vs 41). Ghi nhận lỗi: A: "Tập trung cao nhất" cả 2 chưa diễn giải được | B: Sai tên Phạm Minh Chính thành “Fan Mingzheng”; đồng thời cũng bỏ nhiều ý về mức độ và phạm vi hành động. Điểm thấp — nên kiểm tra thủ công trước khi đưa vào tính tương quan.
A18: 17 | B18: =Du_lieu_goc!C19 -> 政府也灵活调整财政、货币及其他政策以保障宏观经济稳定，促进生产经营；开展切实、有效帮扶政策、机制。 | C18: =Du_lieu_goc!D19 -> Chính phủ cũng sẽ điều chỉnh linh hoạt chính sách tài khóa, tiền tệ và các chính sách khác để giữ vững ổn định vĩ mô, bảo đảm các cân đối lớn, thúc đẩy sản xuất kinh doanh, tập trung ưu tiên triển khai các cơ chế, chính sách hỗ trợ thiết thực, hiệu quả . | D18: Chính phủ cũng linh hoạt điều chỉnh các chính sách tài khóa, tiền tệ và các chính sách khác để đảm bảo ổn định kinh tế vĩ mô, thúc đẩy sản xuất kinh doanh; triển khai các chính sách, cơ chế hỗ trợ thiết thực, hiệu quả. | E18: Chính phủ cũng đã điều chỉnh linh hoạt các chính sách tài khóa, tiền tệ và các chính sách khác nhằm bảo đảm ổn định kinh tế vĩ mô và thúc đẩy sản xuất kinh doanh; triển khai các chính sách, cơ chế hỗ trợ thiết thực, hiệu quả. | F18: Người 1 | G18: 90 | H18: 80 | I18: =I17 -> Người 2 | J18: 76 | K18: 50 | L18: Tham chiếu dùng “sẽ điều chỉnh”, còn bản dịch bỏ dấu hiệu tương lai, làm yếu thông tin thời của chính sách. | M18: [Thắc mắc gốc] câu b sử dụng từ đã làm sai đi ý của câu hiện tại khá nhiều. → [Đối chiếu bản Trung] B dùng thì quá khứ "đã điều chỉnh" trong khi bản Trung là hành động tiếp diễn/tương lai → lệch thì. || Tham chiếu dùng “sẽ điều chỉnh”, nhưng bản dịch chuyển thành “đã điều chỉnh”, làm đổi hành động tương lai thành đã hoàn tất. | O18: 83 | P18: 65 | Q18: LỆCH LỚN 30 điểm giữa chấm chính và chấm chéo — cần rà lại. A vượt B rõ rệt (83 vs 65). Ghi nhận lỗi: A: câu b sử dụng từ đã làm sai đi ý của câu hiện tại khá nhiều. | B: Tham chiếu dùng “sẽ điều chỉnh”, nhưng bản dịch chuyển thành “đã điều chỉnh”, làm đổi hành động tương lai thành đã hoàn tất.
A19: 18 | B19: =Du_lieu_goc!C20 -> 为实现16个指标，范明政提出12个主要任务和措施，其中包括灵活、有效实施防疫措施并复苏、发展经济社会；优先制定、完善体制，改革行政手续，改善营商投资环境。 | C19: =Du_lieu_goc!D20 -> Để thực hiện 16 chỉ tiêu này là 12 nhiệm vụ, giải pháp chủ yếu, trong đó đầu tiên là tập trung thực hiện linh hoạt, hiệu quả mục tiêu vừa phòng, chống dịch COVID-19, vừa phục hồi, phát triển KTXH; tiếp đó là ưu tiên công tác xây dựng, hoàn thiện thể chế, tập trung tháo gỡ khó khăn, cải cách thủ tục hành chính, cải thiện môi trường đầu tư kinh doanh. | D19: Để thực hiện 16 chỉ tiêu, Phạm Minh Chính đã đề xuất 12 nhiệm vụ và giải pháp trọng tâm, bao gồm việc triển khai linh hoạt, hiệu quả các biện pháp phòng chống dịch bệnh, đồng thời phục hồi và phát triển kinh tế - xã hội; ưu tiên xây dựng, hoàn thiện thể chế, cải cách thủ tục hành chính, cải thiện môi trường kinh doanh và đầu tư. | E19: Để đạt được 16 chỉ số, Fan Mingzheng đề xuất 12 nhiệm vụ, biện pháp chính, bao gồm thực hiện linh hoạt, hiệu quả các biện pháp phòng chống dịch bệnh và phục hồi, phát triển kinh tế, xã hội; ưu tiên xây dựng và hoàn thiện hệ thống, cải cách thủ tục hành chính, cải thiện môi trường đầu tư, kinh doanh. | F19: Người 1 | G19: 90 | H19: 42 | I19: =I18 -> Người 2 | J19: 78 | K19: 38 | L19: Bỏ thứ tự “đầu tiên/tiếp đó” và ý “tập trung tháo gỡ khó khăn”, làm thiếu một phần đáng kể của nhóm nhiệm vụ. | M19: [Thắc mắc gốc] Sai tên, chỉ tiêu -> chỉ số khá sai nghĩa tuy nhiên không phải là đánh giá chính, → [Đối chiếu bản Trung] B sai tên riêng ("Fan Mingzheng" thay vì Phạm Minh Chính) và dịch 指标 thành "chỉ số" thay vì "chỉ tiêu". || Sai tên Phạm Minh Chính; “16 chỉ tiêu” thành “16 chỉ số”, “hoàn thiện thể chế” thành “hoàn thiện hệ thống” và còn bỏ ý tháo gỡ khó khăn. | O19: 84 | P19: 40 | Q19: Hai người chấm lệch nhẹ (12 điểm). A vượt B rõ rệt (84 vs 40). Ghi nhận lỗi: A: Sai tên, chỉ tiêu -> chỉ số khá sai nghĩa tuy nhiên không phải là đánh giá chính, | B: Sai tên Phạm Minh Chính; “16 chỉ tiêu” thành “16 chỉ số”, “hoàn thiện thể chế” thành “hoàn thiện hệ thống” và còn bỏ ý tháo gỡ khó khăn. Điểm thấp — nên kiểm tra thủ công trước khi đưa vào tính tương quan.
A20: 19 | B20: =Du_lieu_goc!C21 -> 配套、高效开展对外活动，主动、积极融入国际，巩固越南在国际舞台上的地位和威望。 | C20: =Du_lieu_goc!D21 -> Triển khai đồng bộ, hiệu quả hoạt động đối ngoại, chủ động, tích cực hội nhập quốc tế, góp phần củng cố vị thế, uy tín của Việt Nam trên trường quốc tế. | D20: Tổ chức các hoạt động đối ngoại đồng bộ, hiệu quả, chủ động, tích cực hội nhập quốc tế, củng cố vị thế và uy tín của Việt Nam trên trường quốc tế. | E20: Chúng ta sẽ thực hiện các hoạt động đối ngoại hỗ trợ và hiệu quả, chủ động, tích cực hội nhập quốc tế, củng cố vị thế và uy tín của Việt Nam trên trường quốc tế. | F20: Người 1 | G20: 87 | H20: 72 | I20: =I19 -> Người 2 | J20: 90 | K20: 58 | M20: Tự thêm “chúng ta sẽ”, làm thay đổi chủ thể diễn ngôn và thêm nghĩa tương lai không có trong tham chiếu. | O20: 88 | P20: 65 | Q20: Hai người chấm lệch nhẹ (14 điểm). A vượt B rõ rệt (88 vs 65). Ghi nhận lỗi: B: Tự thêm “chúng ta sẽ”, làm thay đổi chủ thể diễn ngôn và thêm nghĩa tương lai không có trong tham chiếu.
A21: 20 | B21: =Du_lieu_goc!C22 -> 有效开展战略伙伴关系、全面伙伴关系框架及自贸协定。 | C21: =Du_lieu_goc!D22 -> Tăng cường các hoạt động ngoại giao cấp cao, khai thác hiệu quả các khuôn khổ quan hệ đối tác chiến lược, đối tác toàn diện, các hiệp định thương mại tự do (FTA). | D21: Triển khai hiệu quả quan hệ đối tác chiến lược, khuôn khổ quan hệ đối tác toàn diện và hiệp định thương mại tự do. | E21: Triển khai hiệu quả các quan hệ đối tác chiến lược, khuôn khổ đối tác toàn diện và các hiệp định thương mại tự do. | F21: Người 1 | G21: 90 | H21: 90 | I21: =I20 -> Người 2 | J21: 70 | K21: 72 | L21: [Thắc mắc gốc] A, không có "các" điểm < B → [Đối chiếu bản Trung] A thiếu mạo từ "các" trước "quan hệ đối tác chiến lược" → kém trôi chảy hơn B một chút. || Bỏ toàn bộ ý “tăng cường các hoạt động ngoại giao cấp cao”, là một nội dung độc lập trong tham chiếu. | M21: Bỏ toàn bộ ý “tăng cường các hoạt động ngoại giao cấp cao”, là một nội dung độc lập trong tham chiếu. | O21: 80 | P21: 81 | Q21: LỆCH LỚN 20 điểm giữa chấm chính và chấm chéo — cần rà lại. A và B tương đương (80 vs 81). Ghi nhận lỗi: A: A, không có "các" điểm < B | B: Bỏ toàn bộ ý “tăng cường các hoạt động ngoại giao cấp cao”, là một nội dung độc lập trong tham chiếu.
A22: 21 | B22: =Du_lieu_goc!C23 -> 进一步做好对外新闻工作、文化外交、海外越南人工作等”。 | C22: =Du_lieu_goc!D23 -> Làm tốt hơn nữa công tác thông tin đối ngoại, ngoại giao văn hóa, công tác người Việt Nam ở nước ngoài và bảo hộ công dân". | D22: Tiếp tục làm tốt công tác báo chí đối ngoại, ngoại giao văn hóa, công tác đối với người Việt Nam ở nước ngoài, v.v. | E22: Chúng tôi sẽ nâng cao hơn nữa công tác thông tấn đối ngoại, ngoại giao văn hóa, công tác người Việt Nam ở nước ngoài, v.v.” | F22: Người 1 | G22: 85 | H22: 75 | I22: =I21 -> Người 2 | J22: 68 | K22: 50 | L22: Bỏ nội dung “bảo hộ công dân” trong tham chiếu. | M22: Bỏ “bảo hộ công dân” và tự thêm “chúng tôi sẽ”, làm thay đổi cả nội dung lẫn chủ thể/tình thái. | N22: [Thắc mắc gốc] Đối chiếu không có "v.v" → [Đối chiếu bản Trung] Đối chiếu không có "v.v." nhưng bản Trung có 等 → A/B thêm "v.v." là đúng với bản Trung. | O22: 76 | P22: 62 | Q22: LỆCH LỚN 25 điểm giữa chấm chính và chấm chéo — cần rà lại. Ghi nhận lỗi: A: Đối chiếu không có "v.v" | B: Bỏ “bảo hộ công dân” và tự thêm “chúng tôi sẽ”, làm thay đổi cả nội dung lẫn chủ thể/tình thái.
A23: 22 | B23: =Du_lieu_goc!C24 -> 范明政表示，相信以全民族大团结及人民对党的领导的信心，越南必将击退疫情，复苏和发展经济社会，推动国家在革新、融入与发展道路上稳步前进。 | C23: =Du_lieu_goc!D24 -> Người đứng đầu Chính phủ tin tưởng với sức mạnh đại đoàn kết toàn dân tộc và niềm tin của Nhân dân vào sự lãnh đạo của Đảng, nhất định Việt Nam sẽ sớm đẩy lùi dịch bệnh để phục hồi và phát triển KTXH, đưa đất nước vững bước tiến lên trên con đường đổi mới, hội nhập và phát triển. | D23: Phạm Minh Chính bày tỏ tin tưởng rằng, với sự đoàn kết toàn dân tộc và niềm tin của nhân dân vào sự lãnh đạo của Đảng, Việt Nam nhất định sẽ đẩy lùi dịch bệnh, phục hồi và phát triển kinh tế - xã hội, đưa đất nước vững bước tiến trên con đường đổi mới, hội nhập và phát triển. | E23: Phạm Minh Chính bày tỏ tin tưởng với sự đoàn kết to lớn của toàn dân tộc và sự tin tưởng của nhân dân vào sự lãnh đạo của Đảng, Việt Nam sẽ đẩy lùi dịch bệnh, phục hồi và phát triển kinh tế, xã hội, thúc đẩy đất nước vững bước trên con đường đổi mới, hội nhập và phát triển. | F23: Người 1 | G23: 90 | H23: 88 | I23: =I22 -> Người 2 | J23: 88 | K23: 86 | N23: [Thắc mắc gốc] "PMC" ở đâu ra vậy → [Đối chiếu bản Trung] Đối chiếu dùng "Người đứng đầu Chính phủ", A/B dùng đích danh "Phạm Minh Chính" — bản Trung ghi 范明政 nên A/B sát hơn. | O23: 89 | P23: 87 | Q23: Hai người chấm thống nhất cao. A và B tương đương (89 vs 87). Ghi nhận lỗi: A: "PMC" ở đâu ra vậy
A24: 23 | B24: =Du_lieu_goc!C25 -> 叙利亚政府和反对派日前正式同意在联合国的参与下开始修宪进程。 | C24: =Du_lieu_goc!D25 -> Chính phủ Syria và phe đối lập vừa chính thức nhất trí khởi động tiến trình soạn thảo nội dung sửa đổi hiếp pháp, dưới sự tham gia của Liên Hợp Quốc. | D24: Chính phủ Syria và phe đối lập mới đây đã chính thức đồng ý khởi động tiến trình sửa đổi hiến pháp dưới sự tham gia của Liên Hợp Quốc. | E24: Chính phủ Syria và các đảng đối lập mới đây đã chính thức đồng ý bắt đầu quá trình sửa đổi hiến pháp với sự tham gia của Liên hợp quốc. | F24: Người 1 | G24: 92 | H24: 88 | I24: =I23 -> Người 2 | J24: 90 | K24: 84 | O24: 91 | P24: 86 | Q24: Hai người chấm thống nhất cao.
A25: 24 | B25: =Du_lieu_goc!C26 -> 叙利亚宪法委员会在日内瓦举行的本轮磋商计划持续一周，希望达成全面、长期的法律基础，解决叙利亚各党派的分歧，为更广泛的政治进程敞开大门。 | C25: =Du_lieu_goc!D26 -> Vòng đàm phán Ủy ban Hiến pháp Syria (SCC) tiến hành tại Geneva lần này dự kiến kéo dài trong 1 tuần, với mong muốn đạt được một cơ sở pháp lý toàn diện, lâu dài, khắc phục sự khác biệt giữa các đảng phái tại Syria và mở ra cánh cửa cho một tiến trình chính trị rộng lớn hơn. | D25: Vòng đàm phán lần này của Ủy ban Hiến pháp Syria tại Geneva dự kiến kéo dài một tuần, với hy vọng đạt được nền tảng pháp lý toàn diện và lâu dài, giải quyết những bất đồng giữa các bên tại Syria, mở đường cho một tiến trình chính trị rộng lớn hơn. | E25: Vòng tham vấn hiện tại do Ủy ban Hiến pháp Syria tổ chức tại Geneva dự kiến ​​sẽ kéo dài trong một tuần, với hy vọng đạt được cơ sở pháp lý toàn diện và lâu dài, giải quyết những khác biệt giữa các đảng phái ở Syria và mở ra cánh cửa cho một tiến trình chính trị rộng lớn hơn. | F25: Người 1 | G25: 90 | H25: 88 | I25: =I24 -> Người 2 | J25: 88 | K25: 94 | L25: [Thắc mắc gốc] A < B, do A không có "đảng phái" → [Đối chiếu bản Trung] A thiếu "đảng phái" khi dịch 各党派 → B đầy đủ hơn ở chi tiết này. | O25: 89 | P25: 91 | Q25: Hai người chấm lệch nhẹ (6 điểm). A và B tương đương (89 vs 91). Ghi nhận lỗi: A: A < B, do A không có "đảng phái"
A26: 25 | B26: =Du_lieu_goc!C27 -> 过去2年，该委员会开了5次会，但由于反对派和叙利亚政府之间存在分歧，均未取得进展，尽管该中东国家数百万人须等待新宪法生效后才能举行全国大选。 | C26: =Du_lieu_goc!D27 -> Trong 2 năm qua, ủy ban này đã nhóm họp 5 lần, nhưng kết quả thu lại không đáng kể do các bất đồng giữa phe đối lập và Chính phủ Syria, bất chấp việc hàng triệu người dân quốc gia Trung Đông vẫn đang mòn mỏi chờ đợi một cuộc bầu cử quy mô toàn quốc, vốn chỉ được tiến hành sau khi có hiến pháp mới. | D26: Trong 2 năm qua, ủy ban này đã họp 5 lần, nhưng do những bất đồng giữa phe đối lập và chính phủ Syria, không có tiến triển nào đạt được, mặc dù hàng triệu người dân nước này đang chờ đợi cuộc tổng tuyển cử diễn ra sau khi hiến pháp mới có hiệu lực. | E26: Ủy ban đã họp năm lần trong hai năm qua nhưng không đạt được tiến bộ nào do sự khác biệt giữa phe đối lập và chính phủ Syria, ngay cả khi hàng triệu người dân ở quốc gia Trung Đông này phải chờ hiến pháp mới có hiệu lực trước khi các cuộc bầu cử quốc gia được tổ chức. | F26: Người 1 | G26: 90 | H26: 87 | I26: =I25 -> Người 2 | J26: 84 | K26: 83 | L26: “Kết quả không đáng kể” bị đổi thành “không có tiến triển nào”, làm tăng mức độ phủ định so với tham chiếu. | M26: [Thắc mắc gốc] Đọc thấy B sai nghĩa? → [Đối chiếu bản Trung] B đảo cấu trúc câu và dùng "ngay cả khi", làm quan hệ nhân-quả mờ hơn bản Trung. || “Kết quả không đáng kể” bị đổi thành “không đạt được tiến bộ nào”, làm tăng mức độ phủ định so với tham chiếu. | O26: 87 | P26: 85 | Q26: Hai người chấm lệch nhẹ (6 điểm). A và B tương đương (87 vs 85). Ghi nhận lỗi: A: Đọc thấy B sai nghĩa? | B: “Kết quả không đáng kể” bị đổi thành “không đạt được tiến bộ nào”, làm tăng mức độ phủ định so với tham chiếu.
A27: 26 | B27: =Du_lieu_goc!C28 -> 因此，观察人士希望本轮对话有助于叙利亚制定双方都能接受的新宪法。 | C27: =Du_lieu_goc!D28 -> Vì vậy, giới quan sát hy vọng vòng đối thoại lần này giúp Syria có một bản hiến pháp mới mà các bên cùng có thể chấp nhận. | D27: Vì vậy, các nhà quan sát hy vọng vòng đối thoại lần này sẽ giúp Syria soạn thảo một hiến pháp mới mà cả hai bên đều có thể chấp nhận. | E27: Vì vậy, giới quan sát hy vọng vòng đối thoại này sẽ giúp Syria xây dựng một hiến pháp mới được cả hai bên chấp nhận. | F27: Người 1 | G27: 90 | H27: 90 | I27: =I26 -> Người 2 | J27: 93 | K27: 93 | O27: 92 | P27: 92 | Q27: Hai người chấm thống nhất cao. A và B tương đương (92 vs 92).
A28: 27 | B28: =Du_lieu_goc!C29 -> 叙利亚10多年的冲突中，西方国家、阿拉伯国家与支持叙利亚政府的俄罗斯、中国和伊朗之间存在深刻分歧。 | C28: =Du_lieu_goc!D29 -> Hơn 10 năm xung đột ở Syria, với sự bất đồng sâu sắc giữa một bên là các nước phương Tây cùng khối Arab và bên kia là Nga, Trung Quốc và Iran. | D28: Trong cuộc xung đột kéo dài hơn một thập kỷ tại Syria, các nước phương Tây, các quốc gia Ả Rập và Nga, Trung Quốc, Iran ủng hộ chính phủ Syria đã tồn tại những bất đồng sâu sắc. | E28: Trong cuộc xung đột kéo dài hơn 10 năm ở Syria, đã có sự khác biệt sâu sắc giữa các nước phương Tây, các nước Ả Rập và Nga, Trung Quốc, Iran ủng hộ chính phủ Syria. | F28: Người 1 | G28: 88 | H28: 87 | I28: =I27 -> Người 2 | J28: 72 | K28: 72 | L28: Cấu trúc câu làm mờ quan hệ đối lập giữa một bên là phương Tây/Ả Rập và bên kia là Nga–Trung–Iran. | M28: Cấu trúc câu làm mờ quan hệ đối lập giữa hai nhóm quốc gia được nêu trong tham chiếu. | N28: [Thắc mắc gốc] Có "ủng hộ" ở bản gốc thật à → [Đối chiếu bản Trung] Bản Trung có 支持叙利亚政府的 (ủng hộ chính phủ Syria) — A/B dịch đúng, đối chiếu lược bỏ ý này. | O28: 80 | P28: 80 | Q28: LỆCH LỚN 16 điểm giữa chấm chính và chấm chéo — cần rà lại. A và B tương đương (80 vs 80). Ghi nhận lỗi: A: Có "ủng hộ" ở bản gốc thật à | B: Cấu trúc câu làm mờ quan hệ đối lập giữa hai nhóm quốc gia được nêu trong tham chiếu.
A29: 28 | B29: =Du_lieu_goc!C30 -> 目前，叙利亚政府已经夺回大部分领土的控制权，但基础设施遭到严重破坏，需要数十年或数百年的时间才能恢复。 | C29: =Du_lieu_goc!D30 -> Đến nay, Chính phủ Syria đã giành lại gần hết quyền kiểm soát lãnh thổ nhưng hạ tầng cơ sở đã bị tàn phá nặng nề phải mất hàng chục hoặc hàng trăm năm sau mới phục hồi. | D29: Hiện tại, chính phủ Syria đã giành lại quyền kiểm soát phần lớn lãnh thổ, nhưng cơ sở hạ tầng bị tàn phá nặng nề, cần nhiều thập kỷ hoặc thậm chí hàng thế kỷ để phục hồi. | E29: Chính phủ Syria đã giành lại quyền kiểm soát phần lớn lãnh thổ, nhưng cơ sở hạ tầng đã bị hư hại nghiêm trọng và sẽ phải mất hàng thập kỷ hoặc thế kỷ để phục hồi. | F29: Người 1 | G29: 90 | H29: 90 | I29: =I28 -> Người 2 | J29: 82 | K29: 80 | L29: “Gần hết quyền kiểm soát lãnh thổ” bị giảm thành “phần lớn lãnh thổ”, làm thay đổi phạm vi định lượng. | M29: “Gần hết quyền kiểm soát lãnh thổ” bị giảm thành “phần lớn lãnh thổ”, làm thay đổi phạm vi định lượng. | O29: 86 | P29: 85 | Q29: Hai người chấm lệch nhẹ (10 điểm). A và B tương đương (86 vs 85). Ghi nhận lỗi: A: “Gần hết quyền kiểm soát lãnh thổ” bị giảm thành “phần lớn lãnh thổ”, làm thay đổi phạm vi định lượng. | B: “Gần hết quyền kiểm soát lãnh thổ” bị giảm thành “phần lớn lãnh thổ”, làm thay đổi phạm vi định lượng.
A30: 29 | B30: =Du_lieu_goc!C31 -> 令人担忧的是，儿童是叙利亚长期冲突中最大的受害者。 | C30: =Du_lieu_goc!D31 -> Đáng quan ngại, là trẻ em chính là nạn nhân chịu ảnh hưởng lớn nhất trong cuộc xung đột kéo dài ở Syria. | D30: Điều đáng lo ngại là trẻ em là những nạn nhân lớn nhất trong cuộc xung đột kéo dài ở Syria. | E30: Điều đáng lo ngại là trẻ em là nạn nhân lớn nhất trong cuộc xung đột kéo dài ở Syria. | F30: Người 1 | G30: 95 | H30: 95 | I30: =I29 -> Người 2 | J30: 94 | K30: 94 | O30: 94 | P30: 94 | Q30: Hai người chấm thống nhất cao. A và B tương đương (94 vs 94).
A31: 30 | B31: =Du_lieu_goc!C32 -> 据联合国儿童基金会的报告，过去10年，超过100万儿童在叙利亚境外的难民营出生，350万儿童失学，90%的叙利亚儿童急需救济。 | C31: =Du_lieu_goc!D32 -> Theo báo cáo của Quỹ Nhi đồng Liên Hợp Quốc, trong vòng 10 năm qua, hơn 1 triệu trẻ em được sinh ra trong các trại tị nạn ngoài Syria, 3,5 triệu trẻ em thất học, 90% trẻ em Syria đang rất cần được hỗ trợ cả về vật chất và tâm lý. | D31: Theo báo cáo của Quỹ Nhi đồng Liên Hợp Quốc, trong 10 năm qua, hơn 1 triệu trẻ em đã chào đời tại các trại tị nạn bên ngoài Syria, 3,5 triệu trẻ em không được đến trường và 90% trẻ em Syria đang rất cần viện trợ nhân đạo. | E31: Theo báo cáo của Quỹ Nhi đồng Liên hợp quốc, hơn 1 triệu trẻ em đã được sinh ra trong các trại tị nạn bên ngoài Syria trong 10 năm qua, 3,5 triệu trẻ em không được đến trường và 90% trẻ em Syria đang cần được cứu trợ khẩn cấp. | F31: Người 1 | G31: 90 | H31: 90 | I31: =I30 -> Người 2 | J31: 76 | K31: 74 | L31: Tham chiếu nêu hỗ trợ “cả về vật chất và tâm lý”, nhưng bản dịch khái quát thành “viện trợ nhân đạo”, làm mất hai nội dung cụ thể. | M31: Tham chiếu nêu hỗ trợ “cả về vật chất và tâm lý”, nhưng bản dịch chỉ nói “cứu trợ khẩn cấp”, làm mất hai nội dung cụ thể. | N31: [Thắc mắc gốc] Ý cuối chưa rõ có cùng ý nghĩa không → [Đối chiếu bản Trung] Ý cuối: bản Trung 急需救济 (cần cứu trợ khẩn cấp); đối chiếu mở rộng thành "hỗ trợ cả vật chất và tâm lý" → đối chiếu tự thêm. | O31: 83 | P31: 82 | Q31: LỆCH LỚN 16 điểm giữa chấm chính và chấm chéo — cần rà lại. A và B tương đương (83 vs 82). Ghi nhận lỗi: A: Ý cuối chưa rõ có cùng ý nghĩa không | B: Tham chiếu nêu hỗ trợ “cả về vật chất và tâm lý”, nhưng bản dịch chỉ nói “cứu trợ khẩn cấp”, làm mất hai nội dung cụ thể.
A32: 31 | B32: =Du_lieu_goc!C33 -> 而叙利亚冲突每天都在继续。 | C32: =Du_lieu_goc!D33 -> Trong khi đó, xung đột ở Syria vẫn tiếp tục diễn ra hàng ngày. | D32: Và cuộc xung đột ở Syria vẫn tiếp diễn hàng ngày. | E32: Và cuộc xung đột ở Syria vẫn tiếp diễn mỗi ngày. | F32: Người 1 | G32: 95 | H32: 95 | I32: =I31 -> Người 2 | J32: 93 | K32: 93 | N32: [Thắc mắc gốc] "Trong khi đó" và "và"? → [Đối chiếu bản Trung] Khác biệt "Trong khi đó" / "Và" chỉ là liên từ chuyển ý, không ảnh hưởng nghĩa. | O32: 94 | P32: 94 | Q32: Hai người chấm thống nhất cao. A và B tương đương (94 vs 94). Ghi nhận lỗi: A: "Trong khi đó" và "và"?
A33: 32 | B33: =Du_lieu_goc!C34 -> 这令人担忧，尽管得到了许多国际组织和有关国家的支持，但叙利亚恢复和平仍然是一个难题。 | C33: =Du_lieu_goc!D34 -> Điều này làm dấy lên quan ngại mặc dù được nhiều tổ chức quốc tế và các quốc gia liên quan quan tâm hỗ trợ, tuy nhiên, việc lập lại hòa bình cho Syria vẫn còn là bài toán khó. | D33: Điều này thật đáng lo ngại, mặc dù đã nhận được sự ủng hộ của nhiều tổ chức quốc tế và các quốc gia liên quan, nhưng việc khôi phục hòa bình cho Syria vẫn là một thách thức lớn. | E33: Điều này thật đáng lo ngại. Bất chấp sự hỗ trợ của nhiều tổ chức quốc tế và các nước liên quan, việc khôi phục hòa bình ở Syria vẫn là một bài toán khó. | F33: Người 1 | G33: 90 | H33: 88 | I33: =I32 -> Người 2 | J33: 88 | K33: 92 | O33: 89 | P33: 90 | Q33: Hai người chấm thống nhất cao. A và B tương đương (89 vs 90).
A34: 33 | B34: =Du_lieu_goc!C35 -> 越南政府颁布关于“安全、灵活适应并有效控制新冠肺炎疫情”的第128号决议后，各部门、各地方迅速从“封闭”模式转为“新常态”模式。 | C34: =Du_lieu_goc!D35 -> Sau khi chính phủ Việt Nam ban bố nghị quyết 128 “thích ứng an toàn, linh hoạt, kiểm soát hiệu quả dịch Covid-19”, mhiều bộ, ngành, địa phương tại Việt Nam nhanh chóng chuyển từ trạng thái “đóng cửa” sang trạng thái thích ứng bình thường mới. | D34: Sau khi Chính phủ Việt Nam ban hành Nghị quyết số 128 về "An toàn, linh hoạt thích ứng và kiểm soát hiệu quả dịch COVID-19", các bộ, ngành, địa phương đã nhanh chóng chuyển đổi từ trạng thái "đóng băng" sang trạng thái "bình thường mới". | E34: Sau khi Chính phủ ban hành Nghị quyết số 128 về “Thích ứng an toàn, linh hoạt và kiểm soát hiệu quả dịch bệnh Covid-19”, nhiều sở, ngành, địa phương đã nhanh chóng chuyển từ chế độ “đóng cửa” sang chế độ “bình thường mới”. | F34: Người 1 | G34: 80 | H34: 90 | I34: =I33 -> Người 2 | J34: 82 | K34: 75 | M34: “Bộ, ngành” bị đổi thành “sở, ngành”, làm sai cấp đơn vị được nhắc đến. | O34: 81 | P34: 82 | Q34: LỆCH LỚN 15 điểm giữa chấm chính và chấm chéo — cần rà lại. A và B tương đương (81 vs 82). Ghi nhận lỗi: B: “Bộ, ngành” bị đổi thành “sở, ngành”, làm sai cấp đơn vị được nhắc đến.
A35: 34 | B35: =Du_lieu_goc!C36 -> 九龙江平原地区集中防控疫情3个月后，多个省市目前已经基本控制了疫情。 | C35: =Du_lieu_goc!D36 -> Tại đồng bằng sông Cửu Long, sau 3 tháng tập trung phòng, chống dịch Covid-19, đến nay nhiều tỉnh đã cơ bản kiểm soát được dịch. | D35: Sau 3 tháng tập trung phòng chống dịch tại vùng đồng bằng sông Cửu Long, nhiều tỉnh thành hiện đã cơ bản kiểm soát được dịch bệnh. | E35: Ba tháng sau khi phòng chống dịch tập trung ở đồng bằng Cửu Long Giang, nhiều tỉnh, thành phố hiện đã cơ bản kiểm soát được dịch bệnh. | F35: Người 1 | G35: 90 | H35: 78 | I35: =I34 -> Người 2 | J35: 94 | K35: 78 | O35: 92 | P35: 78 | Q35: Hai người chấm thống nhất cao.
A36: 35 | B36: =Du_lieu_goc!C37 -> 其中，同塔省约有200家企业已恢复活动。 | C36: =Du_lieu_goc!D37 -> Trong đó, riêng tỉnh Đồng Tháp, hiện có hơn 200 doanh nghiệp đã dần sản xuất trở lại. | D36: Trong đó, tỉnh Đồng Tháp có khoảng 200 doanh nghiệp đã hoạt động trở lại. | E36: Trong đó, khoảng 200 doanh nghiệp ở tỉnh Đồng Tháp đã hoạt động trở lại. | F36: Người 1 | G36: 88 | H36: 88 | I36: =I35 -> Người 2 | J36: 82 | K36: 82 | O36: 85 | P36: 85 | Q36: Hai người chấm lệch nhẹ (6 điểm). A và B tương đương (85 vs 85).
A37: 36 | B37: =Du_lieu_goc!C38 -> 落实第128号决议，谅山省为口岸商品通关活动安全、快速进行提供便利条件，确保实现防控疫情、发展经济“双胜利”。 | C37: =Du_lieu_goc!D38 -> Triển khai thực hiện Nghị quyết 128, tỉnh Lạng Sơn đã và đang tạo điều kiện thuận lợi để hoạt động thông quan hàng hóa qua cửa khẩu diễn ra an toàn, nhanh chóng, đảm bảo thực hiện mục tiêu kép vừa phòng chống dịch vừa phục hồi phát triển kinh tế. | D37: Để thực hiện Nghị quyết số 128, tỉnh Lạng Sơn đã tạo điều kiện thuận lợi cho hoạt động thông quan hàng hóa tại cửa khẩu diễn ra an toàn, nhanh chóng, đảm bảo đạt được "thắng lợi kép" trong công tác phòng chống dịch bệnh và phát triển kinh tế. | E37: Thực hiện Nghị quyết số 128, tỉnh Lạng Sơn tạo điều kiện thuận lợi cho hoạt động thông quan hàng hóa tại cảng diễn ra an toàn, nhanh chóng, bảo đảm “chiến thắng kép” trong công tác phòng, chống dịch bệnh và phát triển kinh tế. | F37: Người 1 | G37: 88 | H37: 72 | I37: =I36 -> Người 2 | J37: 80 | K37: 65 | M37: “Thông quan hàng hóa qua cửa khẩu” bị đổi thành “tại cảng”, làm sai địa điểm/loại cửa ngõ thông quan. | O37: 84 | P37: 68 | Q37: Hai người chấm lệch nhẹ (8 điểm). A vượt B rõ rệt (84 vs 68). Ghi nhận lỗi: B: “Thông quan hàng hóa qua cửa khẩu” bị đổi thành “tại cảng”, làm sai địa điểm/loại cửa ngõ thông quan.
A38: 37 | B38: =Du_lieu_goc!C39 -> 交通运输部副部长黎庭寿说：“货运和客运是我部最主要的2个领域。 | C38: =Du_lieu_goc!D39 -> Thứ trưởng Lê Đình Thọ khẳng định: “Ngành giao thông có 2 lĩnh vực chính là: vận tải hàng hóa và vận tải hành khách. | D38: Thứ trưởng Bộ Giao thông Vận tải Lê Đình Thọ cho biết: "Vận tải hàng hóa và vận tải hành khách là hai lĩnh vực chính yếu nhất của Bộ chúng tôi." | E38: Thứ trưởng Bộ GTVT Lê Đình Thọ cho biết: “Vận tải hàng hóa và hành khách là hai lĩnh vực quan trọng nhất của Bộ chúng ta. | F38: Người 1 | G38: 92 | H38: 90 | I38: =I37 -> Người 2 | J38: 90 | K38: 76 | M38: Tham chiếu nói về hai lĩnh vực chính của ngành giao thông; bản dịch chuyển sang “Bộ chúng ta”, làm đổi chủ thể và thêm đại từ người nghe. | N38: [Thắc mắc gốc] Bản đối chiếu không nhắc thứ trưởng bộ gtvt → [Đối chiếu bản Trung] Đối chiếu không nhắc chức danh "Thứ trưởng Bộ GTVT" nhưng bản Trung có 交通运输部副部长 → A/B đúng, đối chiếu lược bỏ. | O38: 91 | P38: 83 | Q38: Hai người chấm lệch nhẹ (14 điểm). Ghi nhận lỗi: A: Bản đối chiếu không nhắc thứ trưởng bộ gtvt | B: Tham chiếu nói về hai lĩnh vực chính của ngành giao thông; bản dịch chuyển sang “Bộ chúng ta”, làm đổi chủ thể và thêm đại từ người nghe.
A39: 38 | B39: =Du_lieu_goc!C40 -> 现在落实第128号决议，我们将审视、颁布新规定，确保符合决议目的、要求及卫生部相关防疫规定。 | C39: =Du_lieu_goc!D40 -> Khi triển khai Nghị quyết 128, chúng tôi rà soát, ban hành quy định mới để phù hợp với mục đích yêu cầu, đặc biệt là quy định mới của Bộ y tế. | D39: Hiện tại, để thực hiện Nghị quyết số 128, chúng tôi sẽ xem xét và ban hành các quy định mới, đảm bảo tuân thủ mục đích, yêu cầu của nghị quyết cũng như các quy định phòng chống dịch bệnh liên quan của Bộ Y tế. | E39: Nay để thực hiện Nghị quyết số 128, chúng ta sẽ rà soát, ban hành các quy định mới bảo đảm đúng mục đích, yêu cầu của Nghị quyết và các quy định phòng chống dịch có liên quan của Bộ Y tế. | F39: Người 1 | G39: 88 | H39: 88 | I39: =I38 -> Người 2 | J39: 78 | K39: 72 | L39: Tham chiếu mô tả việc rà soát, ban hành ở hiện tại và nhấn mạnh quy định mới của Bộ Y tế; bản dịch chuyển sang “sẽ” và làm mờ điểm nhấn này. | M39: Bản dịch chuyển “chúng tôi rà soát, ban hành” thành “chúng ta sẽ”, vừa đổi đại từ vừa đổi thời của hành động. | O39: 83 | P39: 80 | Q39: LỆCH LỚN 16 điểm giữa chấm chính và chấm chéo — cần rà lại. A và B tương đương (83 vs 80). Ghi nhận lỗi: A: Tham chiếu mô tả việc rà soát, ban hành ở hiện tại và nhấn mạnh quy định mới của Bộ Y tế; bản dịch chuyển sang “sẽ” và làm mờ điểm nhấn này. | B: Bản dịch chuyển “chúng tôi rà soát, ban hành” thành “chúng ta sẽ”, vừa đổi đại từ vừa đổi thời của hành động.
A40: 39 | B40: =Du_lieu_goc!C41 -> 巴地头顿省人民委员会副主席陈文俊表示，该省正逐步从防控疫情状态转为安全适应状态。 | C40: =Du_lieu_goc!D41 -> Theo ông Trần Văn Tuấn, Phó Chủ tịch UBND tỉnh Bà Rịa – Vũng Tàu, tỉnh đang chuyển trang thái từ chống dịch sang phòng dịch và thích ứng an toàn. | D40: Phó Chủ tịch Ủy ban Nhân dân tỉnh Bà Rịa - Vũng Tàu, ông Trần Văn Tuấn, cho biết tỉnh đang dần chuyển từ trạng thái kiểm soát dịch bệnh sang trạng thái thích ứng an toàn. | E40: Ông Trần Văn Tuấn, Phó Chủ tịch UBND tỉnh Bà Rịa-Vũng Tàu, cho biết tỉnh đang dần chuyển từ trạng thái phòng, chống dịch sang trạng thái thích ứng an toàn. | F40: Người 1 | G40: 90 | H40: 90 | I40: =I39 -> Người 2 | J40: 78 | K40: 80 | O40: 84 | P40: 85 | Q40: Hai người chấm lệch nhẹ (12 điểm). A và B tương đương (84 vs 85).
A41: 40 | B41: =Du_lieu_goc!C42 -> 在该地区各国正加快完成疫苗接种计划的背景下，欧洲正逐步适应并采取措施促进经济增长。 | C41: =Du_lieu_goc!D42 -> Tuy nhiên, với nhiều giải pháp, kinh tế châu Âu đang có dấu hiệu tăng trưởng tích cực. | D41: Trong bối cảnh các quốc gia trong khu vực đang đẩy nhanh tiến độ hoàn thành kế hoạch tiêm chủng, châu Âu đang dần thích ứng và thực hiện các biện pháp thúc đẩy tăng trưởng kinh tế. | E41: Châu Âu đang dần thích nghi và thực hiện các biện pháp nhằm thúc đẩy tăng trưởng kinh tế khi các nước trong khu vực đẩy nhanh việc hoàn thành các chương trình tiêm chủng của mình. | F41: Người 1 | G41: 90 | H41: 90 | I41: =I40 -> Người 2 | J41: 55 | K41: 55 | L41: Tham chiếu chỉ nói kinh tế châu Âu đang có dấu hiệu tăng trưởng tích cực nhờ nhiều giải pháp; bản dịch chuyển sang bối cảnh tiêm chủng và các biện pháp thúc đẩy tăng trưởng. | M41: Tham chiếu chỉ nói kinh tế châu Âu đang có dấu hiệu tăng trưởng tích cực nhờ nhiều giải pháp; bản dịch chuyển sang bối cảnh tiêm chủng và các biện pháp thúc đẩy tăng trưởng. | N41: Đối chiếu chỉ là diễn giải rất thoáng, bỏ hẳn bối cảnh tiêm chủng có trong bản Trung. | O41: 90 | P41: 90 | Q41: [LỖI DỮ LIỆU GỐC] Đối chiếu chỉ là diễn giải rất thoáng, bỏ hẳn bối cảnh tiêm chủng có trong bản Trung. Điểm chấm chéo bị kéo xuống rất thấp vì so với bản đối chiếu; điểm final chấm lại theo độ trung thực với BẢN TRUNG. Khuyến nghị: LOẠI câu này khỏi tính tương quan, hoặc ghi rõ trong Limitations.
A42: 41 | B42: =Du_lieu_goc!C43 -> 放宽防疫措施是经济复苏的“杠杆” | C42: =Du_lieu_goc!D43 -> Nới lỏng các biện pháp kiểm soát dịch bệnh là “đòn bẩy” phục hồi nền kinh tế | D42: Nới lỏng các biện pháp phòng dịch là "đòn bẩy" cho sự phục hồi kinh tế. | E42: Nới lỏng các biện pháp phòng chống dịch là “đòn bẩy” phục hồi kinh tế | F42: Người 1 | G42: 90 | H42: 92 | I42: =I41 -> Người 2 | J42: 94 | K42: 95 | O42: 92 | P42: 94 | Q42: Hai người chấm thống nhất cao. A và B tương đương (92 vs 94).
A43: 42 | B43: =Du_lieu_goc!C44 -> 据初步评估，在欧洲各国放松防疫限制措施以及政府提供资助后，欧盟经济继续显示积极的复苏迹象。 | C43: =Du_lieu_goc!D44 -> Theo đánh giá sơ bộ, khu vực EU tiếp tục cho thấy những dấu hiệu phục hồi tích cực khi các quốc gia nới lỏng nhiều biện pháp hạn chế nhằm ngăn chặn đại dịch COVID-19 và sự hỗ trợ liên tục của các Chính phủ. | D43: Theo đánh giá ban đầu, kinh tế Liên minh châu Âu tiếp tục cho thấy những dấu hiệu phục hồi tích cực sau khi các nước châu Âu nới lỏng các biện pháp phòng chống dịch bệnh và chính phủ cung cấp các khoản tài trợ. | E43: Theo đánh giá sơ bộ, nền kinh tế EU tiếp tục có dấu hiệu phục hồi tích cực sau khi các nước châu Âu nới lỏng các hạn chế chống dịch và các chính phủ cung cấp kinh phí. | F43: Người 1 | G43: 90 | H43: 90 | I43: =I42 -> Người 2 | J43: 86 | K43: 88 | N43: [Thắc mắc gốc] Không thấy nhắc về kinh tế nhưng A, B đều nhắc → [Đối chiếu bản Trung] Bản Trung có 欧盟经济 (kinh tế EU) → A/B nhắc "kinh tế" là đúng; đối chiếu diễn đạt gọn hơn. | O43: 88 | P43: 89 | Q43: Hai người chấm thống nhất cao. A và B tương đương (88 vs 89). Ghi nhận lỗi: A: Không thấy nhắc về kinh tế nhưng A, B đều nhắc
A44: 43 | B44: =Du_lieu_goc!C45 -> 欧盟各国经济复苏的驱动力是向企业（制造业）和净出口投资。 | C44: =Du_lieu_goc!D45 -> Động lực cho sự phục hồi kinh tế của các nước EU là đầu tư của doanh nghiệp (trong lĩnh vực sản xuất), xuất khẩu ròng. | D44: Động lực phục hồi kinh tế của các nước Liên minh Châu Âu là đầu tư vào doanh nghiệp (sản xuất) và xuất khẩu ròng. | E44: Sự phục hồi kinh tế ở các nước EU được thúc đẩy bởi đầu tư vào doanh nghiệp (sản xuất) và xuất khẩu ròng. | F44: Người 1 | G44: 92 | H44: 92 | I44: =I43 -> Người 2 | J44: 70 | K44: 70 | L44: “Đầu tư của doanh nghiệp” bị đổi thành “đầu tư vào doanh nghiệp”, làm đổi quan hệ chủ thể–đối tượng của động lực phục hồi. | M44: “Đầu tư của doanh nghiệp” bị đổi thành “đầu tư vào doanh nghiệp”, làm đổi quan hệ chủ thể–đối tượng. | O44: 81 | P44: 81 | Q44: LỆCH LỚN 22 điểm giữa chấm chính và chấm chéo — cần rà lại. A và B tương đương (81 vs 81). Ghi nhận lỗi: A: “Đầu tư của doanh nghiệp” bị đổi thành “đầu tư vào doanh nghiệp”, làm đổi quan hệ chủ thể–đối tượng của động lực phục hồi. | B: “Đầu tư của doanh nghiệp” bị đổi thành “đầu tư vào doanh nghiệp”, làm đổi quan hệ chủ thể–đối tượng.
A45: 44 | B45: =Du_lieu_goc!C46 -> 尽管欧元区通胀率居高不下，但原因是受疫情及相关因素影响，这个通胀率仍被认为是暂时的。 | C45: =Du_lieu_goc!D46 -> Mặc dù tỷ lệ lạm phát của khu vực đồng Euro vẫn duy trì ở mức cao, mức lạm phát này vẫn được đánh giá mang tính chất tạm thời do các yếu tố liên quan đến đại dịch. | D45: Mặc dù tỷ lệ lạm phát của khu vực đồng Euro vẫn ở mức cao, nhưng do ảnh hưởng của đại dịch và các yếu tố liên quan, tỷ lệ lạm phát này vẫn được xem là tạm thời. | E45: Mặc dù tỷ lệ lạm phát tại khu vực đồng Euro vẫn ở mức cao nhưng vẫn được coi là tạm thời do ảnh hưởng của dịch bệnh và các yếu tố liên quan. | F45: Người 1 | G45: 90 | H45: 88 | I45: =I44 -> Người 2 | J45: 92 | K45: 93 | O45: 91 | P45: 90 | Q45: Hai người chấm thống nhất cao. A và B tương đương (91 vs 90).
A46: 45 | B46: =Du_lieu_goc!C47 -> 疫情后经济复苏基金是欧盟至2027年长期预算计划的一部分，旨在克服疫情爆发造成的经济和社会后果。 | C46: =Du_lieu_goc!D47 -> Quỹ phục hồi kinh tế hậu COVID-19 là một phần trong gói ngân sách dài hạn đến năm 2027 của EU, nhằm giải quyết những hậu quả về kinh tế và xã hội sau khi đại dịch COVID-19 bùng phát. | D46: Quỹ phục hồi kinh tế sau đại dịch là một phần trong kế hoạch ngân sách dài hạn của Liên minh Châu Âu đến năm 2027, nhằm khắc phục những hậu quả kinh tế và xã hội do đại dịch gây ra. | E46: Quỹ phục hồi kinh tế sau dịch bệnh là một phần trong kế hoạch ngân sách dài hạn của EU cho đến năm 2027 và được thiết kế để khắc phục hậu quả kinh tế và xã hội do dịch bệnh bùng phát. | F46: Người 1 | G46: 92 | H46: 90 | I46: =I45 -> Người 2 | J46: 93 | K46: 92 | O46: 92 | P46: 91 | Q46: Hai người chấm thống nhất cao. A và B tương đương (92 vs 91).
A47: 46 | B47: =Du_lieu_goc!C48 -> 7月中旬，欧盟还正式批准了12个国家提交的复苏计划，为欧盟首次发放无偿援助和贷款铺平了道路。 | C47: =Du_lieu_goc!D48 -> Giữa tháng 7, EU cũng chính thức thông qua kế hoạch phục hồi do 12 nước đệ trình, nhằm mở đường cho đợt giải ngân các khoản tài trợ và cho vay đầu tiên của khối này. | D47: Vào giữa tháng 7, Liên minh châu Âu cũng đã chính thức phê duyệt các kế hoạch phục hồi do 12 quốc gia đệ trình, mở đường cho việc EU lần đầu tiên giải ngân viện trợ không hoàn lại và cho vay. | E47: Giữa tháng 7, EU cũng chính thức phê duyệt các kế hoạch phục hồi do 12 nước đệ trình, mở đường cho EU lần đầu tiên cấp viện trợ và cho vay miễn phí. | F47: Người 1 | G47: 90 | H47: 80 | I47: =I46 -> Người 2 | J47: 90 | K47: 58 | M47: “Các khoản tài trợ và cho vay” bị diễn đạt thành “viện trợ và cho vay miễn phí”, làm sai bản chất của khoản vay. | N47: [Thắc mắc gốc] A, B đều diễ giải sai bản chất viện trợ → [Đối chiếu bản Trung] Cả A và B đều diễn giải chưa chuẩn bản chất 无偿援助 (viện trợ không hoàn lại): B dịch thành "viện trợ miễn phí". | O47: 90 | P47: 69 | Q47: LỆCH LỚN 22 điểm giữa chấm chính và chấm chéo — cần rà lại. A vượt B rõ rệt (90 vs 69). Ghi nhận lỗi: A: A, B đều diễ giải sai bản chất viện trợ | B: “Các khoản tài trợ và cho vay” bị diễn đạt thành “viện trợ và cho vay miễn phí”, làm sai bản chất của khoản vay.
A48: 47 | B48: =Du_lieu_goc!C49 -> 越南党和国家明确可持续减贫是国家革新、建设和发展的贯穿性、统领性、重要的大主张。 | C48: =Du_lieu_goc!D49 -> Đảng và Nhà nước Việt Nam xác định công tác giảm nghèo bền vững là chủ trương lớn, quan trọng, nhất quán, xuyên suốt trong quá trình thực hiện công cuộc đổi mới, xây dựng và phát triển đất nước. | D48: Đảng và Nhà nước Việt Nam xác định giảm nghèo bền vững là chủ trương xuyên suốt, bao trùm, quan trọng trong công cuộc đổi mới, xây dựng và phát triển đất nước. | E48: Đảng và Nhà nước Việt Nam đã xác định rõ giảm nghèo bền vững là vấn đề xuyên suốt, hàng đầu và quan trọng trong công cuộc đổi mới, xây dựng và phát triển đất nước. | F48: Người 1 | G48: 88 | H48: 88 | I48: =I47 -> Người 2 | J48: 82 | K48: 68 | M48: “Chủ trương lớn, nhất quán, xuyên suốt” bị đổi thành “vấn đề xuyên suốt, hàng đầu”, làm thay đổi tính chất của chủ trương. | O48: 85 | P48: 78 | Q48: LỆCH LỚN 20 điểm giữa chấm chính và chấm chéo — cần rà lại. Ghi nhận lỗi: B: “Chủ trương lớn, nhất quán, xuyên suốt” bị đổi thành “vấn đề xuyên suốt, hàng đầu”, làm thay đổi tính chất của chủ trương.
A49: 48 | B49: =Du_lieu_goc!C50 -> 越南还制定了2021-2025年阶段贫困线标准，为农村地区人均月收入150万盾，城市地区200万盾。 | C49: =Du_lieu_goc!D50 -> Việt Nam cũng xây dựng chuẩn nghèo giai đoạn 2021-2025 với tiêu chí thu nhập bình quân đầu người một tháng tại khu vực nông thôn là 1.500.000 đồng, khu vực thành thị là 2.000.000 đồng | D49: Việt Nam cũng đã ban hành chuẩn nghèo giai đoạn 2021-2025, với mức thu nhập bình quân đầu người hàng tháng là 1,5 triệu đồng đối với khu vực nông thôn và 2 triệu đồng đối với khu vực thành thị. | E49: Việt Nam cũng đã đưa ra chuẩn nghèo cho giai đoạn 2021-2025, đó là thu nhập bình quân đầu người mỗi tháng là 1,5 triệu đồng ở nông thôn và 2 triệu đồng ở thành thị. | F49: Người 1 | G49: 93 | H49: 92 | I49: =I48 -> Người 2 | J49: 92 | K49: 92 | O49: 92 | P49: 92 | Q49: Hai người chấm thống nhất cao. A và B tương đương (92 vs 92).
A50: 49 | B50: =Du_lieu_goc!C51 -> 该计划的目标是多维、包容、可持续减贫，防止返贫和新致贫发生；支持贫困户和贫困者脱离最低生活标准，享有国家多维贫困线规定的基本社会服务，提高生活质量；支持沿海地区和海岛贫困地区脱离贫困和特困状况。 | C50: =Du_lieu_goc!D51 -> Mục tiêu của kế hoạch nói trên là giảm nghèo đa chiều, bao trùm, bền vững, hạn chế tái nghèo và phát sinh nghèo; hỗ trợ người nghèo, hộ nghèo vượt lên mức sống tối thiểu, tiếp cận các dịch vụ xã hội cơ bản theo chuẩn nghèo đa chiều quốc gia, nâng cao chất lượng cuộc sống; hỗ trợ các huyện nghèo, xã đặc biệt khó khăn vùng bãi ngang ven biển và hải đảo thoát khỏi tình trạng nghèo, đặc biệt khó khăn. | D50: Mục tiêu của kế hoạch là giảm nghèo đa chiều, bao trùm và bền vững, ngăn ngừa tái nghèo và phát sinh nghèo mới; hỗ trợ các hộ nghèo và người nghèo thoát khỏi mức sống tối thiểu, được hưởng các dịch vụ xã hội cơ bản theo quy định của đường nghèo đa chiều quốc gia, nâng cao chất lượng cuộc sống; hỗ trợ các vùng nghèo, vùng đặc biệt khó khăn ở khu vực ven biển và hải đảo thoát khỏi tình trạng nghèo và đặc biệt khó khăn. | E50: Mục tiêu của kế hoạch là giảm nghèo đa chiều, toàn diện, bền vững và ngăn ngừa tái nghèo, nghèo mới; hỗ trợ hộ nghèo, người nghèo thoát khỏi mức sống tối thiểu, được hưởng các dịch vụ xã hội cơ bản theo chuẩn nghèo đa chiều quốc gia và nâng cao chất lượng cuộc sống; hỗ trợ các vùng ven biển, vùng nghèo hải đảo thoát nghèo, nghèo cùng cực. | F50: Người 1 | G50: 88 | H50: 85 | I50: =I49 -> Người 2 | J50: 72 | K50: 68 | L50: Mất các đơn vị cụ thể “huyện nghèo, xã đặc biệt khó khăn”; “chuẩn nghèo” còn bị diễn đạt sai thành “đường nghèo”. | M50: Mất các đơn vị “huyện nghèo, xã đặc biệt khó khăn” và đổi “đặc biệt khó khăn” thành “nghèo cùng cực”. | O50: 80 | P50: 76 | Q50: LỆCH LỚN 17 điểm giữa chấm chính và chấm chéo — cần rà lại. Ghi nhận lỗi: A: Mất các đơn vị cụ thể “huyện nghèo, xã đặc biệt khó khăn”; “chuẩn nghèo” còn bị diễn đạt sai thành “đường nghèo”. | B: Mất các đơn vị “huyện nghèo, xã đặc biệt khó khăn” và đổi “đặc biệt khó khăn” thành “nghèo cùng cực”.
A51: 50 | B51: =Du_lieu_goc!C52 -> 该计划还投资发展贫困核心地区的社会经济基础设施，提高贫困人口的收入和生活质量，培训职业技能，创造良好的就业机会，支持弱势群体脱贫。 | C51: =Du_lieu_goc!D52 -> Chương trình cũng đầu tư phát triển hạ tầng kinh tế - xã hội vùng lõi nghèo, nâng cao thu nhập, chất lượng cuộc sống của người nghèo, đào tạo kỹ năng nghề, tạo việc làm tốt, hỗ trợ đối tượng yếu thế không rơi vào tình trạng nghèo đói. | D51: Kế hoạch này còn đầu tư phát triển cơ sở hạ tầng kinh tế - xã hội tại các khu vực nghèo khó, nâng cao thu nhập và chất lượng cuộc sống cho người dân nghèo, đào tạo kỹ năng nghề, tạo cơ hội việc làm tốt, hỗ trợ các nhóm yếu thế thoát nghèo. | E51: Kế hoạch cũng đầu tư phát triển cơ sở hạ tầng kinh tế - xã hội ở các vùng đói nghèo cốt lõi, cải thiện thu nhập và chất lượng cuộc sống của người nghèo, đào tạo kỹ năng nghề, tạo cơ hội việc làm tốt và hỗ trợ các nhóm thiệt thòi thoát nghèo. | F51: Người 1 | G51: 90 | H51: 88 | I51: =I50 -> Người 2 | J51: 62 | K51: 60 | L51: Tham chiếu nói hỗ trợ nhóm yếu thế “không rơi vào tình trạng nghèo đói”, nhưng bản dịch thành “thoát nghèo”, làm đổi quan hệ mục tiêu. | M51: Tham chiếu nói hỗ trợ nhóm yếu thế “không rơi vào tình trạng nghèo đói”, nhưng bản dịch thành “thoát nghèo”, làm đổi quan hệ mục tiêu. | O51: 76 | P51: 74 | Q51: LỆCH LỚN 28 điểm giữa chấm chính và chấm chéo — cần rà lại. A và B tương đương (76 vs 74). Ghi nhận lỗi: A: Tham chiếu nói hỗ trợ nhóm yếu thế “không rơi vào tình trạng nghèo đói”, nhưng bản dịch thành “thoát nghèo”, làm đổi quan hệ mục tiêu. | B: Tham chiếu nói hỗ trợ nhóm yếu thế “không rơi vào tình trạng nghèo đói”, nhưng bản dịch thành “thoát nghèo”, làm đổi quan hệ mục tiêu.
A52: 51 | B52: =Du_lieu_goc!C53 -> 越南还推动实现包容性减贫目标，特别是提高收入和保障基本社会服务，如就业、教育、医疗、住房、清洁生活用水和卫生、信息等，以进一步为所有人、在任何地方、任何时候、从各个方向消除饥饿贫困。 | C52: =Du_lieu_goc!D53 -> Việt Nam cũng đẩy mạnh thực hiện mục tiêu giảm nghèo bao trùm, nhất là nâng cao thu nhập và bảo đảm các chiều dịch vụ xã hội cơ bản như việc làm, giáo dục, y tế, nhà ở, nước sạch sinh hoạt và vệ sinh, thông tin để tiến tới xoá bỏ nghèo đói cho mọi người, ở mọi nơi, mọi thời điểm và mọi chiều. | D52: Việt Nam cũng thúc đẩy các mục tiêu giảm nghèo bao trùm, đặc biệt là tăng thu nhập và đảm bảo các dịch vụ xã hội cơ bản như việc làm, giáo dục, y tế, nhà ở, nước sạch và vệ sinh, thông tin, v.v., nhằm xóa bỏ nạn đói và nghèo đói cho tất cả mọi người, ở mọi nơi, mọi lúc, từ mọi phía. | E52: Việt Nam cũng thúc đẩy mục tiêu giảm nghèo toàn diện, đặc biệt là tăng thu nhập và đảm bảo các dịch vụ xã hội cơ bản như việc làm, giáo dục, chăm sóc y tế, nhà ở, nước sạch và vệ sinh, thông tin... nhằm xóa đói hơn nữa tình trạng đói nghèo cho mọi người, mọi nơi, mọi lúc và từ mọi hướng. | F52: Người 1 | G52: 87 | H52: 87 | I52: =I51 -> Người 2 | J52: 88 | K52: 74 | N52: [Thắc mắc gốc] Có "..." không, do đối chiếu không có → [Đối chiếu bản Trung] Bản Trung có 等 (v.v.) → A/B giữ "v.v." là đúng, đối chiếu lược bỏ. | O52: 88 | P52: 80 | Q52: Hai người chấm lệch nhẹ (13 điểm). Ghi nhận lỗi: A: Có "..." không, do đối chiếu không có
A53: 52 | B53: =Du_lieu_goc!C54 -> 越南疫情防控工作正出现积极信号。 | C53: =Du_lieu_goc!D54 -> Việt Nam đang ghi nhận những tín hiệu tích cực trong công tác phòng chống dịch. | D53: Công tác phòng chống dịch bệnh tại Việt Nam đang có những tín hiệu tích cực. | E53: Công tác phòng, chống dịch của Việt Nam đang có những tín hiệu tích cực. | F53: Người 1 | G53: 93 | H53: 93 | I53: =I52 -> Người 2 | J53: 95 | K53: 95 | O53: 94 | P53: 94 | Q53: Hai người chấm thống nhất cao. A và B tương đương (94 vs 94).
A54: 53 | B54: =Du_lieu_goc!C55 -> 这是越南着手恢复生产，发展经济的时候。 | C54: =Du_lieu_goc!D55 -> Đây là thời điểm Việt Nam có thể bắt tay nhanh chóng vào khôi phục sản xuất, phát triển kinh tế. | D54: Đây là thời điểm Việt Nam bắt tay vào khôi phục sản xuất, phát triển kinh tế. | E54: Đây là thời điểm Việt Nam bắt đầu khôi phục sản xuất và phát triển kinh tế. | F54: Người 1 | G54: 88 | H54: 87 | I54: =I53 -> Người 2 | J54: 84 | K54: 82 | N54: [Thắc mắc gốc] Thiếu "có thể" → [Đối chiếu bản Trung] Cả A và B đều thiếu sắc thái "có thể" mà đối chiếu có; bản Trung không có tình thái này → không phải lỗi bản dịch. | O54: 86 | P54: 84 | Q54: Hai người chấm thống nhất cao. A và B tương đương (86 vs 84). Ghi nhận lỗi: A: Thiếu "có thể"
A55: 54 | B55: =Du_lieu_goc!C56 -> 各级领导人几天来做出的指导表明越南恢复增长的巨大决心。 | C55: =Du_lieu_goc!D56 -> Một loạt chỉ đạo mang tính định hướng của các cấp lãnh đạo được đưa ra trong những ngày qua cho thấy quyết tâm rất lớn của Việt Nam trong việc lấy lại đà tăng trưởng. | D55: Những chỉ đạo của các cấp lãnh đạo trong những ngày qua cho thấy quyết tâm phục hồi tăng trưởng mạnh mẽ của Việt Nam. | E55: Sự chỉ đạo của lãnh đạo các cấp trong những ngày qua thể hiện quyết tâm cao độ của Việt Nam trong việc khôi phục tăng trưởng. | F55: Người 1 | G55: 88 | H55: 88 | I55: =I54 -> Người 2 | J55: 92 | K55: 92 | O55: 90 | P55: 90 | Q55: Hai người chấm thống nhất cao. A và B tương đương (90 vs 90).
A56: 55 | B56: =Du_lieu_goc!C57 -> 政府10月11日颁布的决议暂时规定“安全、灵活适应，有效控制疫情"。 | C56: =Du_lieu_goc!D57 -> Ngày 10-11 chính phủ ban bố nghị quyết 128/NQ-CP quy định tạm thời “Thích ứng an toàn, linh hoạt, kiểm soát hiệu quả dịch COVID -19” | D56: Nghị quyết do chính phủ ban hành ngày 11 tháng 10 quy định tạm thời "an toàn, thích ứng linh hoạt, kiểm soát hiệu quả dịch bệnh". | E56: Nghị quyết của Chính phủ ban hành ngày 11/10 tạm thời quy định “an toàn, thích ứng linh hoạt và kiểm soát dịch hiệu quả”. | F56: Người 1 | G56: 88 | H56: 87 | I56: =I55 -> Người 2 | J56: 91 | K56: 91 | N56: [Thắc mắc gốc] Có vẻ không có cụm "128/NQ-CP" → [Đối chiếu bản Trung] Đối chiếu thêm mã số "128/NQ-CP" không có trong bản Trung → đối chiếu tự bổ sung thông tin ngoài. | O56: 90 | P56: 89 | Q56: Hai người chấm thống nhất cao. A và B tương đương (90 vs 89). Ghi nhận lỗi: A: Có vẻ không có cụm "128/NQ-CP"
A57: 56 | B57: =Du_lieu_goc!C58 -> 在世界经济恢复趋势中避免错失经济发展机遇 | C57: =Du_lieu_goc!D58 -> Không để nền kinh tế bị lỡ nhịp trong xu hướng hồi phục kinh tế thế giới | D57: Trong xu hướng phục hồi kinh tế toàn cầu, cần tránh bỏ lỡ cơ hội phát triển kinh tế. | E57: Tránh bỏ lỡ cơ hội phát triển kinh tế trong xu hướng phục hồi kinh tế thế giới | F57: Người 1 | G57: 88 | H57: 88 | I57: =I56 -> Người 2 | J57: 86 | K57: 88 | N57: [Thắc mắc gốc] A < B → [Đối chiếu bản Trung] Đề xuất A thấp hơn B: A đổi câu tiêu đề thành câu trần thuật có "cần", B giữ dạng tiêu đề sát hơn. | O57: 87 | P57: 88 | Q57: Hai người chấm thống nhất cao. A và B tương đương (87 vs 88). Ghi nhận lỗi: A: A < B
A58: 57 | B58: =Du_lieu_goc!C59 -> 国内航空公司10月10日重新运营国内航班。 | C58: =Du_lieu_goc!D59 -> Từ ngày 10/10, các hãng hàng không trong nước cũng đã khai thác trở lại đường bay nội địa. | D58: Các hãng hàng không nội địa nối lại hoạt động bay nội địa từ ngày 10 tháng 10. | E58: Các hãng hàng không trong nước sẽ khai thác trở lại các chuyến bay nội địa từ ngày 10/10. | F58: Người 1 | G58: 90 | H58: 90 | I58: =I57 -> Người 2 | J58: 93 | K58: 48 | M58: Tham chiếu nêu các chuyến bay “đã khai thác trở lại” từ 10/10; bản dịch chuyển thành “sẽ khai thác trở lại”, đổi quá khứ thành tương lai. | O58: 92 | P58: 69 | Q58: LỆCH LỚN 42 điểm giữa chấm chính và chấm chéo — cần rà lại. A vượt B rõ rệt (92 vs 69). Ghi nhận lỗi: B: Tham chiếu nêu các chuyến bay “đã khai thác trở lại” từ 10/10; bản dịch chuyển thành “sẽ khai thác trở lại”, đổi quá khứ thành tương lai.
A59: 58 | B59: =Du_lieu_goc!C60 -> 此前，塔利班领导人还参加了在首都喀布尔哈米德卡尔扎伊国际机场举行的接受卡塔尔、中国、阿联酋、巴基斯坦和乌兹别克斯坦援助活动。 | C59: =Du_lieu_goc!D60 -> Tiến trình này được xúc tiến chỉ ít ngày sau khi lãnh đạo Taliban có cuộc hội đàm với Simon Gass, đại diện cấp cao tại Afghanistan của Thủ tướng Anh Boris Johnson (hôm 5/10). | D59: Trước đó, các lãnh đạo Taliban đã tham gia hoạt động tiếp nhận viện trợ từ Qatar, Trung Quốc, Các Tiểu vương quốc Ả Rập Thống nhất, Pakistan và Uzbekistan tại Sân bay Quốc tế Hamid Karzai ở thủ đô Kabul. | E59: Trước đó, thủ lĩnh Taliban cũng tham gia một sự kiện được tổ chức tại sân bay quốc tế Hamid Karzai ở thủ đô Kabul để nhận viện trợ từ Qatar, Trung Quốc, Các Tiểu vương quốc Ả Rập Thống nhất, Pakistan và Uzbekistan. | F59: Người 1 | G59: 90 | H59: 90 | I59: =I58 -> Người 2 | J59: 8 | K59: 8 | L59: Bản dịch nói về hoạt động nhận viện trợ tại sân bay, trong khi tham chiếu nói về cuộc hội đàm với Simon Gass; nội dung gần như khác hẳn. | M59: Bản dịch nói về hoạt động nhận viện trợ tại sân bay, trong khi tham chiếu nói về cuộc hội đàm với Simon Gass; nội dung gần như khác hẳn. | N59: Đối chiếu nói về cuộc hội đàm với Simon Gass — KHÁC HOÀN TOÀN nội dung bản Trung (nhận viện trợ tại sân bay Kabul). Lỗi dóng hàng của kho ngữ liệu VLSP. | O59: 90 | P59: 90 | Q59: [LỖI DỮ LIỆU GỐC] Đối chiếu nói về cuộc hội đàm với Simon Gass — KHÁC HOÀN TOÀN nội dung bản Trung (nhận viện trợ tại sân bay Kabul). Lỗi dóng hàng của kho ngữ liệu VLSP. Điểm chấm chéo bị kéo xuống rất thấp vì so với bản đối chiếu; điểm final chấm lại theo độ trung thực với BẢN TRUNG. Khuyến nghị: LOẠI câu này khỏi tính tương quan, hoặc ghi rõ trong Limitations.
A60: 59 | B60: =Du_lieu_goc!C61 -> 多名地区和西方分析人士一致认为，塔利班领导人积极接触国际社会，旨在打破孤立并寻求国际承认。 | C60: =Du_lieu_goc!D61 -> Nhiều nhà phân tích khu vực và phương Tây có chung nhận định rằng: việc lãnh đạo Taliban tích cực tham gia các cuộc tiếp xúc với thế giới nhằm mục tiêu phá vỡ thế cô lập, tìm kiếm sự cộng nhận quốc tế. | D60: Nhiều nhà phân tích khu vực và phương Tây cùng nhận định rằng, các nhà lãnh đạo Taliban đang tích cực tiếp xúc với cộng đồng quốc tế nhằm phá vỡ sự cô lập và tìm kiếm sự công nhận quốc tế. | E60: Nhiều nhà phân tích khu vực và phương Tây đồng ý rằng các thủ lĩnh Taliban tích cực tham gia với cộng đồng quốc tế nhằm phá vỡ sự cô lập và tìm kiếm sự công nhận của quốc tế. | F60: Người 1 | G60: 90 | H60: 88 | I60: =I59 -> Người 2 | J60: 90 | K60: 85 | O60: 90 | P60: 86 | Q60: Hai người chấm thống nhất cao.
A61: 60 | B61: =Du_lieu_goc!C62 -> 然而，在阿富汗可能发生严重人道主义灾难的背景下，在对塔利班施压的同时，国际社会也在努力寻找解决方案，以防止这个南亚国家人道主义局势恶化。 | C61: =Du_lieu_goc!D62 -> Tuy nhiên, trong bối cảnh có thể xảy một thậm họa nhân đạo nghiêm trọng tại Afghanistan, cùng với việc gây sức ép lên Taliban, cộng đồng quốc tế cũng đang nỗ lực tìm giải pháp ngăn chặn tình trạng nhân đạo đang ngày càng xấu đi tại quốc gia Nam Á. | D61: Tuy nhiên, trong bối cảnh có nguy cơ xảy ra thảm họa nhân đạo nghiêm trọng tại Afghanistan, song song với việc gây áp lực lên Taliban, cộng đồng quốc tế cũng đang nỗ lực tìm kiếm các giải pháp nhằm ngăn chặn tình hình nhân đạo tại quốc gia Nam Á này xấu đi. | E61: Tuy nhiên, trong bối cảnh có thể xảy ra thảm họa nhân đạo nghiêm trọng ở Afghanistan, đồng thời gây áp lực lên Taliban, cộng đồng quốc tế cũng đang nỗ lực tìm giải pháp ngăn chặn tình hình nhân đạo ở quốc gia Nam Á này xấu đi. | F61: Người 1 | G61: 90 | H61: 90 | I61: =I60 -> Người 2 | J61: 93 | K61: 93 | N61: [Thắc mắc gốc] Tham chiếu còn sai chính tả → [Đối chiếu bản Trung] Bản đối chiếu có lỗi chính tả ("thậm họa", "xảy một") — vấn đề chất lượng dữ liệu gốc, không phải lỗi bản dịch. | O61: 92 | P61: 92 | Q61: Hai người chấm thống nhất cao. A và B tương đương (92 vs 92). Ghi nhận lỗi: A: Tham chiếu còn sai chính tả
A62: 61 | B62: =Du_lieu_goc!C63 -> 救济上千万面临粮食危机的阿富汗人是一项紧迫而必要的任务，而建设一个稳定、进步的社会则是阿富汗国家和人民的根本、长远之计。 | C62: =Du_lieu_goc!D63 -> Cứu trợ hàng triệu người Afghanistan đang đối mặt với tình trạng khủng hoảng lương thực là nhiệm vụ cần thiết, cấp bách, tuy nhiên, giải pháp căn cơ, lâu dài cho đất nước và người dân Afghanistan, vẫn là xây dựng một xã hội ổn định, tiến bộ. | D62: Cứu trợ hàng chục triệu người Afghanistan đang đối mặt với khủng hoảng lương thực là một nhiệm vụ cấp bách và cần thiết, trong khi xây dựng một xã hội ổn định, tiến bộ là kế sách căn bản, lâu dài cho quốc gia và nhân dân Afghanistan. | E62: Cứu trợ hàng chục triệu người dân Afghanistan đang gặp khủng hoảng lương thực là nhiệm vụ cấp bách, cần thiết, xây dựng xã hội ổn định, tiến bộ là giải pháp căn bản, lâu dài cho đất nước và người dân Afghanistan. | F62: Người 1 | G62: 90 | H62: 90 | I62: =I61 -> Người 2 | J62: 65 | K62: 65 | L62: “Hàng triệu người Afghanistan” bị tăng thành “hàng chục triệu”, làm sai quy mô của thông tin định lượng. | M62: “Hàng triệu người Afghanistan” bị tăng thành “hàng chục triệu”, làm sai quy mô của thông tin định lượng. | N62: [Thắc mắc gốc] Có vẻ chưa diễn đạt ý "tuy nhiên" → [Đối chiếu bản Trung] Cả A và B đều chưa thể hiện quan hệ tương phản "tuy nhiên" mà đối chiếu có; bản Trung dùng 而 → sắc thái nhẹ hơn. | O62: 78 | P62: 78 | Q62: LỆCH LỚN 25 điểm giữa chấm chính và chấm chéo — cần rà lại. A và B tương đương (78 vs 78). Ghi nhận lỗi: A: Có vẻ chưa diễn đạt ý "tuy nhiên" | B: “Hàng triệu người Afghanistan” bị tăng thành “hàng chục triệu”, làm sai quy mô của thông tin định lượng.
A63: 62 | B63: =Du_lieu_goc!C64 -> 因此，必须要在不仅党内而且整个政治体系进行建设整顿，使之不断纯洁强大。 | C63: =Du_lieu_goc!D64 -> Vì thế, xây dựng chỉnh đốn, làm trong sạch đội ngũ cán bộ không chỉ trong Đảng mà trong cả hệ thống chính trị. | D63: Vì vậy, cần phải tiến hành xây dựng và chỉnh đốn không chỉ trong Đảng mà còn trong toàn bộ hệ thống chính trị, để Đảng và hệ thống chính trị ngày càng trong sạch, vững mạnh. | E63: Vì vậy, chúng ta phải tiến hành xây dựng, chỉnh đốn không chỉ trong Đảng mà cả toàn bộ hệ thống chính trị để nó tiếp tục trong sạch, vững mạnh. | F63: Người 1 | G63: 88 | H63: 85 | I63: =I62 -> Người 2 | J63: 58 | K63: 52 | L63: Tham chiếu nhấn vào xây dựng, chỉnh đốn và làm trong sạch “đội ngũ cán bộ”; bản dịch chuyển trọng tâm sang Đảng và toàn hệ thống chính trị. | M63: Tham chiếu nhấn vào “đội ngũ cán bộ”, nhưng bản dịch chuyển đối tượng sang Đảng/toàn hệ thống chính trị và dùng “nó” mơ hồ. | O63: 73 | P63: 68 | Q63: LỆCH LỚN 33 điểm giữa chấm chính và chấm chéo — cần rà lại. Ghi nhận lỗi: A: Tham chiếu nhấn vào xây dựng, chỉnh đốn và làm trong sạch “đội ngũ cán bộ”; bản dịch chuyển trọng tâm sang Đảng và toàn hệ thống chính trị. | B: Tham chiếu nhấn vào “đội ngũ cán bộ”, nhưng bản dịch chuyển đối tượng sang Đảng/toàn hệ thống chính trị và dùng “nó” mơ hồ.
A64: 63 | B64: =Du_lieu_goc!C65 -> 因为，我们之前只聚焦党内的党建工作。 | C64: =Du_lieu_goc!D65 -> Bởi trước đây chúng ta chỉ tập trung nói trong xây dựng Đảng. | D64: Bởi vì, trước đây chúng tôi chỉ tập trung vào công tác xây dựng Đảng trong nội bộ Đảng. | E64: Bởi vì, trước đây chúng ta chỉ chú trọng đến công tác xây dựng đảng trong nội bộ đảng. | F64: Người 1 | G64: 88 | H64: 88 | I64: =I63 -> Người 2 | J64: 70 | K64: 92 | L64: Tham chiếu dùng “chúng ta”, bản dịch đổi thành “chúng tôi”, làm thay đổi phạm vi người nói/người nghe. | O64: 79 | P64: 90 | Q64: LỆCH LỚN 18 điểm giữa chấm chính và chấm chéo — cần rà lại. Ghi nhận lỗi: A: Tham chiếu dùng “chúng ta”, bản dịch đổi thành “chúng tôi”, làm thay đổi phạm vi người nói/người nghe.
A65: 64 | B65: =Du_lieu_goc!C66 -> 但是，越南共产党是执政党，是领导国家、社会的力量。 | C65: =Du_lieu_goc!D66 -> Nhưng Đảng là Đảng cầm quyền, Đảng lãnh đạo Nhà nước xã hội. | D65: Tuy nhiên, Đảng Cộng sản Việt Nam là đảng cầm quyền, là lực lượng lãnh đạo đất nước và xã hội. | E65: Tuy nhiên, Đảng Cộng sản Việt Nam là đảng cầm quyền, là lực lượng lãnh đạo đất nước và xã hội. | F65: Người 1 | G65: 92 | H65: 92 | I65: =I64 -> Người 2 | J65: 96 | K65: 96 | O65: 94 | P65: 94 | Q65: Hai người chấm thống nhất cao. A và B tương đương (94 vs 94).
A66: 65 | B66: =Du_lieu_goc!C67 -> 越共十三届四中全会上，越共中央总书记阮富仲特别强调了党员要“言行一致”，在执行党和国家决议、政策、法律中发挥表率作用的观点。 | C66: =Du_lieu_goc!D67 -> Tại Hội nghị Trung ương 4, khóa XIII lần này, Tổng Bí thư Nguyễn Phú Trọng nhấn mạnh quan điểm đảng viên phải “nói đi đôi với làm”, gương mẫu chấp hành các nghị quyết, chính sách, pháp luật của Đảng và Nhà nước. | D66: Tại Hội nghị Trung ương 4 khóa XIII Đảng Cộng sản Việt Nam, Tổng Bí thư Nguyễn Phú Trọng đã đặc biệt nhấn mạnh quan điểm về việc đảng viên phải "nói đi đôi với làm", phát huy vai trò tiên phong trong việc thực hiện các nghị quyết, chủ trương, chính sách và pháp luật của Đảng và Nhà nước. | E66: Tại Phiên họp toàn thể lần thứ 4 Ban Chấp hành Trung ương Đảng Cộng sản Việt Nam khóa 13, Tổng Bí thư Ban Chấp hành Trung ương Đảng Cộng sản Việt Nam Nguyễn Phú Trọng đặc biệt nhấn mạnh quan điểm đảng viên phải “nói đi đôi với làm”, phát huy vai trò lãnh đạo trong thực hiện các nghị quyết, chính sách, pháp luật của Đảng, Nhà nước. | F66: Người 1 | G66: 90 | H66: 70 | I66: =I65 -> Người 2 | J66: 85 | K66: 65 | M66: “Gương mẫu chấp hành” bị đổi thành “phát huy vai trò lãnh đạo”, làm sai vai trò của đảng viên. | O66: 88 | P66: 68 | Q66: Hai người chấm thống nhất cao. A vượt B rõ rệt (88 vs 68). Ghi nhận lỗi: B: “Gương mẫu chấp hành” bị đổi thành “phát huy vai trò lãnh đạo”, làm sai vai trò của đảng viên.
A67: 66 | B67: =Du_lieu_goc!C68 -> 阮富仲指出，每一名中央委员会委员的责任，就是要发挥一把手的表率作用。 | C67: =Du_lieu_goc!D68 -> Tổng Bí thư nêu rất rõ trách nhiệm của mỗi Ủy viên Trung ương phải gương mẫu, phải gánh trọng trách là người đứng đầu. | D67: Tổng Bí thư Nguyễn Phú Trọng chỉ ra rằng, trách nhiệm của mỗi Ủy viên Trung ương là phải phát huy vai trò người đứng đầu, làm gương. | E67: Nguyễn Phú Trọng chỉ ra rằng trách nhiệm của mỗi Ủy viên Trung ương là phải làm gương mẫu lãnh đạo. | F67: Người 1 | G67: 90 | H67: 72 | I67: =I66 -> Người 2 | J67: 90 | K67: 70 | N67: [Thắc mắc gốc] Bản dịch không có "Nguyễn Phú Trong" → [Đối chiếu bản Trung] Đối chiếu chỉ ghi "Tổng Bí thư", bản Trung ghi đích danh 阮富仲 → A/B nêu tên là đúng với bản Trung. | O67: 90 | P67: 71 | Q67: Hai người chấm thống nhất cao. A vượt B rõ rệt (90 vs 71). Ghi nhận lỗi: A: Bản dịch không có "Nguyễn Phú Trong"
A68: 67 | B68: =Du_lieu_goc!C69 -> 越共十三届四中全会强调打击由政治思想、道德、生活作风堕落现象引发的消极现象，从而加强建党整党。 | C68: =Du_lieu_goc!D69 -> Hội nghị Trung ương 4 khóa XIII nhấn mạnh chủ trương chống tiêu cực do suy thoái về tư tưởng, chính trị, đạo đức và lối sống để xây dựng, chỉnh đốn Đảng. | D68: Đại hội đại biểu toàn quốc lần thứ XIII của Đảng Cộng sản Việt Nam nhấn mạnh việc đấu tranh chống các hiện tượng tiêu cực bắt nguồn từ sự suy thoái về tư tưởng chính trị, đạo đức, lối sống, qua đó tăng cường công tác xây dựng, chỉnh đốn Đảng. | E68: Phiên họp toàn thể lần thứ 4 Ban Chấp hành Trung ương Đảng Cộng sản Việt Nam khóa 13 nhấn mạnh đấu tranh chống những hiện tượng tiêu cực do suy thoái về tư tưởng chính trị, đạo đức, lối sống, qua đó tăng cường xây dựng đảng, củng cố đảng. | F68: Người 1 | G68: 65 | H68: 80 | I68: =I67 -> Người 2 | J68: 42 | K68: 80 | L68: Tham chiếu là Hội nghị Trung ương 4 khóa XIII, nhưng bản dịch đổi thành Đại hội XIII, làm sai sự kiện. | O68: 54 | P68: 80 | Q68: LỆCH LỚN 23 điểm giữa chấm chính và chấm chéo — cần rà lại. B vượt A rõ rệt (80 vs 54). Ghi nhận lỗi: A: Tham chiếu là Hội nghị Trung ương 4 khóa XIII, nhưng bản dịch đổi thành Đại hội XIII, làm sai sự kiện. Điểm thấp — nên kiểm tra thủ công trước khi đưa vào tính tương quan.
A69: 68 | B69: =Du_lieu_goc!C70 -> 因为，消极现象是其他堕落现象特别是贪腐行为的根源。 | C69: =Du_lieu_goc!D70 -> Bởi tiêu cực là “cái gốc” là nguồn để đi đến những suy thoái khác, đặc biệt là tham nhũng. | D69: Bởi vì, những hiện tượng tiêu cực là nguồn gốc của các hiện tượng suy đồi khác, đặc biệt là hành vi tham nhũng. | E69: Bởi vì những hiện tượng tiêu cực là nguyên nhân sâu xa của những hiện tượng thoái hóa khác, đặc biệt là những hành vi tham nhũng. | F69: Người 1 | G69: 90 | H69: 88 | I69: =I68 -> Người 2 | J69: 92 | K69: 88 | O69: 91 | P69: 88 | Q69: Hai người chấm thống nhất cao. A và B tương đương (91 vs 88).
A70: 69 | B70: =Du_lieu_goc!C71 -> 对此，国会文化、教育和青少年儿童委员会前副主任阮曰职认为，党员不自我锻炼，反而道德、生活作风堕落，那么将滑向“自我演变”、“自我转化”。 | C70: =Du_lieu_goc!D71 -> Về vấn đề này, tiến sỹ Nguyễn Viết Chức, nguyên Phó Chủ nhiệm Ủy ban văn hóa giáo dục thanh niên, thiếu niên nhi đồng của Quốc hội, lập luận rằng: đảng viên không rèn luyện, suy thoái đạo đức lối sống thì sẽ dẫn đến “tự diễn biến”, “tự chuyển hóa” | D70: Về vấn đề này, ông Nguyễn Viết Chức, nguyên Phó Chủ nhiệm Ủy ban Văn hóa, Giáo dục, Thanh niên, Thiếu niên và Nhi đồng của Quốc hội, cho rằng nếu đảng viên không tự tu dưỡng, rèn luyện, mà còn suy đồi đạo đức, lối sống thì sẽ trượt dài vào "tự diễn biến", "tự chuyển hóa". | E70: Về vấn đề này, ông Nguyễn Duyệt Chi, nguyên Phó Chủ nhiệm Ủy ban Văn hóa, Giáo dục, Thanh niên, Nhi đồng của Quốc hội, cho rằng nếu đảng viên không rèn luyện bản thân mà sa sút về đạo đức, lối sống thì sẽ rơi vào tình trạng “tự diễn biến”, “tự chuyển hóa”. | F70: Người 1 | G70: 90 | H70: 55 | I70: =I69 -> Người 2 | J70: 94 | K70: 35 | M70: Sai tên Nguyễn Viết Chức thành Nguyễn Duyệt Chi, nên nhận định bị gán cho sai người. | N70: [Thắc mắc gốc] A, B đều thiếu "Tiến sỹ" → [Đối chiếu bản Trung] Cả A và B đều thiếu học hàm "Tiến sỹ" mà đối chiếu có; bản Trung không có → đối chiếu tự thêm. | O70: 92 | P70: 45 | Q70: LỆCH LỚN 20 điểm giữa chấm chính và chấm chéo — cần rà lại. A vượt B rõ rệt (92 vs 45). Ghi nhận lỗi: A: A, B đều thiếu "Tiến sỹ" | B: Sai tên Nguyễn Viết Chức thành Nguyễn Duyệt Chi, nên nhận định bị gán cho sai người. Điểm thấp — nên kiểm tra thủ công trước khi đưa vào tính tương quan.
A71: 70 | B71: =Du_lieu_goc!C72 -> 理解‘自我演变’是什么，就明白建设纯洁、强大的党就是预防‘自我演变’现象的根本措施”。 | C71: =Du_lieu_goc!D72 -> Phải hiểu tự diễn biến là gì, rõ ràng làm trong sạch vững mạnh đấy chính là biện pháp chống tự diễn biến tận gốc sâu sắc nhất. | D71: Hiểu được "tự diễn biến" là gì thì sẽ hiểu rằng xây dựng Đảng trong sạch, vững mạnh chính là biện pháp căn bản để phòng ngừa hiện tượng "tự diễn biến". | E71: Nếu hiểu “tự diễn biến” là gì thì các bạn sẽ hiểu rằng xây dựng Đảng trong sạch, vững mạnh là biện pháp cơ bản để ngăn chặn hiện tượng “tự diễn biến””. | F71: Người 1 | G71: 90 | H71: 85 | I71: =I70 -> Người 2 | J71: 92 | K71: 80 | O71: 91 | P71: 82 | Q71: Hai người chấm thống nhất cao.
A72: 71 | B72: =Du_lieu_goc!C73 -> 这是党建工作中新的领导指导方针。 | C72: =Du_lieu_goc!D73 -> Đây là phương châm mới trong chỉ đạo thực hiện công tác xây dựng Đảng. | D72: Đây là phương châm chỉ đạo lãnh đạo mới trong công tác xây dựng Đảng. | E72: Đây là đường lối lãnh đạo mới trong công tác xây dựng Đảng. | F72: Người 1 | G72: 85 | H72: 82 | I72: =I71 -> Người 2 | J72: 86 | K72: 74 | N72: [Thắc mắc gốc] Cảm giác dịch khá tệ? → [Đối chiếu bản Trung] Đánh giá "dịch khá tệ": thực tế cả A và B đều sát nghĩa bản Trung; khác biệt với đối chiếu chỉ ở trật tự từ. | O72: 86 | P72: 78 | Q72: Hai người chấm lệch nhẹ (8 điểm). Ghi nhận lỗi: A: Cảm giác dịch khá tệ?
A73: 72 | B73: =Du_lieu_goc!C74 -> 越共十三届四中全会特别强调了发挥党员在建党整党，提高党的战斗力等工作中的先锋作用问题。 | C73: =Du_lieu_goc!D74 -> Hội nghị Trung ương 4 lần này có ý nghĩa quan trọng trong việc phát huy tính tiên phong của cán bộ, đảng viên trong công tác xây dựng, chỉnh đốn Đảng, nâng cao năng lực sức chiến đấu của Đảng. | D73: Đại hội đại biểu toàn quốc lần thứ XIII của Đảng Cộng sản Việt Nam đặc biệt nhấn mạnh vai trò tiên phong của đảng viên trong công tác xây dựng Đảng, chỉnh đốn Đảng và nâng cao năng lực chiến đấu của Đảng. | E73: Phiên họp toàn thể lần thứ 4 Ban Chấp hành Trung ương Đảng Cộng sản Việt Nam khóa 13 đặc biệt nhấn mạnh vấn đề phát huy vai trò tiên phong của đảng viên trong xây dựng, củng cố đảng và nâng cao hiệu quả chiến đấu của đảng. | F73: Người 1 | G73: 65 | H73: 80 | I73: =I72 -> Người 2 | J73: 42 | K73: 80 | L73: Tham chiếu là Hội nghị Trung ương 4 khóa XIII, nhưng bản dịch đổi thành Đại hội XIII, làm sai sự kiện. | M73: [Thắc mắc gốc] "Phiên họp đoàn thể" có giống "hội nghị trung ương" không? → [Đối chiếu bản Trung] B dịch 四中全会 thành "Phiên họp toàn thể lần thứ 4" — không phải cách gọi chuẩn tiếng Việt ("Hội nghị Trung ương 4"). | O73: 54 | P73: 80 | Q73: LỆCH LỚN 23 điểm giữa chấm chính và chấm chéo — cần rà lại. B vượt A rõ rệt (80 vs 54). Ghi nhận lỗi: A: "Phiên họp đoàn thể" có giống "hội nghị trung ương" không? Điểm thấp — nên kiểm tra thủ công trước khi đưa vào tính tương quan.
A74: 73 | B74: =Du_lieu_goc!C75 -> 只要每一名党员都真正发挥表率作用，击退消极，坚决与“自我演变”、“自我转化”现象作斗争，那么越南共产党就一定能不断发展强大，不辜负人民的信任。 | C74: =Du_lieu_goc!D75 -> Chỉ cần mỗi đảng viên thực sự gương mẫu, đẩy lùi tiêu cực, chống lại các biểu hiện “tự diễn biến”, “tự chuyển hóa” thì nhất định Đảng cộng sản Việt Nam vững mạnh, đáp ứng niềm tin tưởng của nhân dân. | D74: Chỉ cần mỗi đảng viên thực sự phát huy vai trò tiên phong, đẩy lùi cái tiêu cực, kiên quyết đấu tranh với hiện tượng "tự diễn biến", "tự chuyển hóa", thì Đảng Cộng sản Việt Nam nhất định sẽ không ngừng phát triển lớn mạnh, không phụ lòng tin của nhân dân. | E74: Chỉ cần mỗi đảng viên thực sự phát huy vai trò gương mẫu, đấu tranh tiêu cực, kiên quyết đấu tranh chống các hiện tượng “tự diễn biến”, “tự chuyển hóa” thì Đảng Cộng sản Việt Nam chắc chắn sẽ tiếp tục lớn mạnh, ngày càng lớn mạnh, xứng đáng với niềm tin của nhân dân. | F74: Người 1 | G74: 90 | H74: 80 | I74: =I73 -> Người 2 | J74: 88 | K74: 80 | O74: 89 | P74: 80 | Q74: Hai người chấm thống nhất cao.
A75: 74 | B75: =Du_lieu_goc!C76 -> 为期三天半的越南共产党第十三届中央委员会第四次会议10月7日在河内落幕。 | C75: =Du_lieu_goc!D76 -> Ngày 7/10/2021, Hội nghị lần thứ 4 Ban chấp hành Trung ương Đảng cộng sản Việt Nam khóa XIII kết thúc sau ba ngày rưỡi làm việc tại Hà Nội. | D75: Hội nghị lần thứ tư, Ban Chấp hành Trung ương Đảng Cộng sản Việt Nam khóa XIII, kéo dài ba ngày rưỡi, đã bế mạc vào ngày 7 tháng 10 tại Hà Nội. | E75: Cuộc họp lần thứ tư kéo dài ba ngày rưỡi của Ban Chấp hành Trung ương Đảng Cộng sản Việt Nam khóa 13 đã kết thúc tại Hà Nội vào ngày 7/10. | F75: Người 1 | G75: 92 | H75: 85 | I75: =I74 -> Người 2 | J75: 93 | K75: 92 | N75: [Thắc mắc gốc] Cảm giác bản trong không có năm 2021 → [Đối chiếu bản Trung] Đối chiếu thêm "2021" vào ngày tháng, bản Trung chỉ ghi 10月7日 → đối chiếu tự bổ sung năm. | O75: 92 | P75: 88 | Q75: Hai người chấm lệch nhẹ (7 điểm). Ghi nhận lỗi: A: Cảm giác bản trong không có năm 2021
A76: 75 | B76: =Du_lieu_goc!C77 -> 实际表明，自越南共产党建党以来，由于有了一位正确、英明的领袖，从而赢得了一场又一场的胜利，创造了20世纪的多个奇迹。 | C76: =Du_lieu_goc!D77 -> Thực tế từ ngày có Đảng, nhân dân Việt Nam đã có người lãnh đạo đúng đắn, sáng suốt, và nhờ thế đã giành được hết thắng lợi này đến thắng lợi khác, lập nên những kỳ tích trong thế kỷ XX. | D76: Thực tế đã chứng minh, kể từ khi Đảng Cộng sản Việt Nam ra đời, nhờ có một người lãnh đạo đúng đắn và sáng suốt, chúng ta đã giành hết thắng lợi này đến thắng lợi khác, tạo nên nhiều kỳ tích của thế kỷ 20. | E76: Thực tế đã chứng minh, từ khi thành lập Đảng Cộng sản Việt Nam nhờ có người lãnh đạo đúng đắn, sáng suốt đã giành hết thắng lợi này đến thắng lợi khác và làm nên nhiều kỳ tích trong thế kỷ 20. | F76: Người 1 | G76: 88 | H76: 88 | I76: =I75 -> Người 2 | J76: 70 | K76: 80 | L76: Tham chiếu nêu “nhân dân Việt Nam” là chủ thể giành thắng lợi; bản dịch đổi thành “chúng ta”, làm thay đổi chủ thể. | N76: [Thắc mắc gốc] Thấy cả A, B đều chưa ổn vì không có "nhân dân" → [Đối chiếu bản Trung] Cả A và B đều thiếu chủ thể "nhân dân Việt Nam" mà đối chiếu có; bản Trung lược chủ ngữ nên A/B dịch bám sát bản Trung. | O76: 79 | P76: 84 | Q76: LỆCH LỚN 18 điểm giữa chấm chính và chấm chéo — cần rà lại. Ghi nhận lỗi: A: Thấy cả A, B đều chưa ổn vì không có "nhân dân"
A77: 76 | B77: =Du_lieu_goc!C78 -> 阮富仲指出：“这次会议提出的新内容是中央委员会按照越共十三大决议精神，不仅在建党整党方面，而且在政治体系建设方面扩大范围；在遏制和打击的同时主动预防、坚决斗争和严厉惩处政治思想、道德、生活作风堕落和贪污腐败等消极现象，同时补充和明确政治思想、道德品质、生活作风堕落以及“自我演变”和“自我转化”的具体表现”。 | C77: =Du_lieu_goc!D78 -> Tổng Bí thư Nguyễn Phú Trọng chỉ rõ:Cái mới của lần này là Trung ương đã mở rộng phạm vi, không chỉ trong xây dựng, chỉnh đốn Đảng mà còn bao gồm cả trong xây dựng hệ thống chính trị đúng theo tinh thần Nghị quyết Đại hội XIII của Đảng; cùng với ngăn chặn, đẩy lùi thì phải chủ động phòng ngừa, kiên quyết đấu tranh, xử lý nghiêm sự suy thoái về tư tưởng chính trị, đạo đức, lối sống và những hành vi tham nhũng, tiêu cực. | D77: Tổng Bí thư Nguyễn Phú Trọng chỉ ra: "Nội dung mới được nêu ra trong hội nghị lần này là Ban Chấp hành Trung ương, theo tinh thần Nghị quyết Đại hội XIII của Đảng, đã mở rộng phạm vi không chỉ trong công tác xây dựng, chỉnh đốn Đảng mà còn cả trong xây dựng hệ thống chính trị; chủ động phòng ngừa, kiên quyết đấu tranh, xử lý nghiêm các biểu hiện tiêu cực như suy thoái về tư tưởng chính trị, đạo đức, lối sống và tham nhũng, tiêu cực, đồng thời bổ sung, làm rõ những biểu hiện cụ thể của suy thoái về tư tưởng chính trị, đạo đức, lối sống cùng với "tự diễn biến", "tự chuyển hóa"." | E77: Nguyễn Phú Trọng chỉ rõ: “Nội dung mới mà kỳ họp này đề ra là Ban Chấp hành Trung ương, theo tinh thần nghị quyết Đại hội XIII của Đảng Cộng sản Việt Nam, không chỉ mở rộng phạm vi xây dựng, củng cố đảng mà còn mở rộng phạm vi xây dựng hệ thống chính trị; đồng thời ngăn chặn, đấu tranh, chủ động phòng ngừa, kiên quyết đấu tranh và trừng phạt nghiêm khắc các hiện tượng tiêu cực như tư tưởng chính trị, đạo đức, suy thoái lối sống, tham nhũng, đồng thời bổ sung, làm rõ những biểu hiện cụ thể về tư tưởng chính trị, đạo đức, lối sống.” suy thoái về phong cách, và “tự diễn biến”, “tự chuyển hóa”. | F77: Người 2 | G77: 78 | H77: 58 | I77: Người 3 | J77: 88 | K77: 88 | L77: Bản dịch thêm cả phần “bổ sung, làm rõ các biểu hiện cụ thể...” không có trong tham chiếu, nên đưa thêm một nội dung độc lập. | M77: Ngoài việc diễn đạt rối chuỗi “ngăn chặn – phòng ngừa – đấu tranh – xử lý nghiêm”, bản dịch còn thêm phần “bổ sung, làm rõ...” không có trong tham chiếu. | O77: 83 | P77: 73 | Q77: LỆCH LỚN 30 điểm giữa chấm chính và chấm chéo — cần rà lại. Ghi nhận lỗi: A: Bản dịch thêm cả phần “bổ sung, làm rõ các biểu hiện cụ thể...” không có trong tham chiếu, nên đưa thêm một nội dung độc lập. | B: Ngoài việc diễn đạt rối chuỗi “ngăn chặn – phòng ngừa – đấu tranh – xử lý nghiêm”, bản dịch còn thêm phần “bổ sung, làm rõ...” không có trong tham chiếu.
A78: 77 | B78: =Du_lieu_goc!C79 -> 道德和生活堕落表现在自私、投机取巧、谋取个人利益、贪名利、贪权、贪污、消极；搞派系，不团结；官僚主义，远离人民，对人民的困难和迫切需要漠不关心。 | C78: =Du_lieu_goc!D79 -> Sự suy thoái về đạo đức, lối sống thể hiện ở chỗ: Sống ích kỷ, thực dụng, cơ hội, vụ lợi, hám danh, hám quyền lực, tham nhũng, tiêu cực; bè phái cục bộ, mất đoàn kết; quan liêu, xa dân, vô cảm trước những khó khăn, bức xúc của dân. | D78: Sự suy đồi về đạo đức và lối sống thể hiện ở việc ích kỷ, cơ hội chủ nghĩa, mưu cầu lợi ích cá nhân, ham danh lợi, ham quyền lực, tham nhũng, tiêu cực; bè phái, mất đoàn kết; quan liêu, xa rời nhân dân, thờ ơ với khó khăn và những nhu cầu cấp thiết của nhân dân. | E78: Sự suy thoái về đạo đức và cuộc sống thể hiện ở tính ích kỷ, cơ hội, trục lợi cá nhân, tham danh lợi, tham quyền lực, tham nhũng, thụ động; tham gia vào các phe phái và mất đoàn kết; quan liêu, xa dân, thờ ơ trước những khó khăn, nhu cầu bức thiết của nhân dân. | F78: Người 2 | G78: 90 | H78: 68 | I78: Người 3 | J78: 84 | K78: 83 | M78: “Tiêu cực” bị dịch thành “thụ động” và “đạo đức, lối sống” thành “đạo đức và cuộc sống”, làm sai các biểu hiện được liệt kê. | O78: 87 | P78: 76 | Q78: LỆCH LỚN 15 điểm giữa chấm chính và chấm chéo — cần rà lại. Ghi nhận lỗi: B: “Tiêu cực” bị dịch thành “thụ động” và “đạo đức, lối sống” thành “đạo đức và cuộc sống”, làm sai các biểu hiện được liệt kê.
A79: 78 | B79: =Du_lieu_goc!C80 -> 阮富仲说：“越共中央高度一致认为，要围绕越共十二届四中全会提出的四项任务和措施，更加配套、彻底地开展更多具体、切实的工作；同时补充和强调以下两项任务和措施：建设各级干部队伍特别是战略性干部队伍，及具备与任务相匹配的能力和威信的领导干部；坚决、坚持反腐倡廉，严惩违法干部”。 | C79: =Du_lieu_goc!D80 -> Tổng bí thư Nguyễn Phú Trọng nêu rõ: Trung ương thống nhất cao phải tiến hành đồng bộ và quyết liệt hơn nữa nhiều công việc cụ thể, thiết thực, tập trung vào 4 nhóm nhiệm vụ, giải pháp mà Hội nghị Trung ương 4 khoá XII đã đề ra; đồng thời bổ sung nhấn mạnh thêm 2 nhóm nhiệm vụ, giải pháp là: Xây dựng đội ngũ cán bộ các cấp, nhất là cấp chiến lược và người đứng đầu đủ phẩm chất, năng lực và uy tín, ngang tầm nhiệm vụ; Kiên quyết, kiên trì đấu tranh phòng, chống tham nhũng, tiêu cực, xử lý nghiêm cán bộ sai phạm. | D79: Tổng Bí thư Nguyễn Phú Trọng nói: "Ban Chấp hành Trung ương Đảng Cộng sản Việt Nam hoàn toàn nhất trí cho rằng, cần triển khai nhiều công việc cụ thể, thiết thực hơn nữa, đồng bộ, quyết liệt hơn nữa, tập trung vào 4 nhiệm vụ, giải pháp đã được đề ra tại Hội nghị Trung ương 4 khóa XII; đồng thời bổ sung, nhấn mạnh thêm 2 nhiệm vụ, giải pháp sau: xây dựng đội ngũ cán bộ các cấp, nhất là cán bộ chiến lược, cán bộ lãnh đạo có đủ phẩm chất, năng lực, uy tín, ngang tầm nhiệm vụ; kiên quyết, kiên trì đấu tranh phòng, chống tham nhũng, tiêu cực, xử lý nghiêm cán bộ sai phạm". | E79: Nguyễn Phú Trọng cho biết: “Trung ương Đảng Cộng sản Việt Nam nhất trí tin tưởng, cần phải tiến hành đồng bộ, xuyên suốt hơn nữa bốn nhiệm vụ, giải pháp do Hội nghị toàn thể lần thứ IV Ban Chấp hành Trung ương Đảng Cộng sản Việt Nam khóa XII đề ra, đồng thời bổ sung, nhấn mạnh hai nhiệm vụ, giải pháp sau: xây dựng đội ngũ cán bộ các cấp, nhất là đội ngũ cán bộ chiến lược và đội ngũ cán bộ lãnh đạo có năng lực, uy tín phù hợp với nhiệm vụ; kiên trì đấu tranh chống tham nhũng, đề cao liêm chính và trừng trị nghiêm khắc những cán bộ vi phạm pháp luật.” | F79: Người 2 | G79: 90 | H79: 70 | I79: Người 3 | J79: 83 | K79: 78 | M79: “Thống nhất cao” bị đổi thành “nhất trí tin tưởng”, đồng thời “quyết liệt” bị đổi thành “xuyên suốt”, làm lệch thái độ và cách thức thực hiện. | O79: 86 | P79: 74 | Q79: Hai người chấm lệch nhẹ (8 điểm). Ghi nhận lỗi: B: “Thống nhất cao” bị đổi thành “nhất trí tin tưởng”, đồng thời “quyết liệt” bị đổi thành “xuyên suốt”, làm lệch thái độ và cách thức thực hiện.
A80: 79 | B80: =Du_lieu_goc!C81 -> 越共中央总书记阮富仲的讲话传递了越南党和国家在新冠肺炎疫情期间继续保障人民生计和健康的信息；也谈到了在今年余下的几个月和明年2022年恢复和发展经济的措施。 | C80: =Du_lieu_goc!D81 -> Những chỉ dẫn trong phát biểu khai mạc Hội nghị của Tổng Bí thư Nguyễn Phú Trọng cho thấy thông điệp mạnh mẽ của Đảng và Nhà nước Việt Nam là tiếp tục đặt mục tiêu an toàn trước dịch bệnh Covid 19; đảm bảo sinh kế, sức khỏe của người dân; song song với đó là phục hồi và phát triển kinh tế trong những tháng còn lại của năm và kế hoạch cho năm 2022 tới. | D80: Bài phát biểu của Tổng Bí thư Đảng Cộng sản Việt Nam Nguyễn Phú Trọng đã truyền tải thông điệp về việc Đảng và Nhà nước Việt Nam tiếp tục đảm bảo sinh kế và sức khỏe cho người dân trong bối cảnh dịch bệnh COVID-19; đồng thời đề cập đến các biện pháp phục hồi và phát triển kinh tế trong những tháng còn lại của năm nay và năm 2022. | E80: Bài phát biểu của Tổng Bí thư Trung ương Đảng Cộng sản Việt Nam Nguyễn Phú Trọng đã truyền tải thông điệp Đảng, Nhà nước Việt Nam sẽ tiếp tục bảo vệ sinh kế, sức khỏe của người dân trong đại dịch Covid-19; đồng thời bàn về các biện pháp phục hồi và phát triển nền kinh tế trong những tháng còn lại của năm nay và năm sau trong năm 2022. | F80: Người 2 | G80: 80 | H80: 78 | I80: Người 3 | J80: 84 | K80: 83 | L80: Bỏ ý Đảng và Nhà nước “tiếp tục đặt mục tiêu an toàn trước dịch bệnh”, là một nội dung độc lập trong tham chiếu. | M80: Bỏ ý Đảng và Nhà nước “tiếp tục đặt mục tiêu an toàn trước dịch bệnh”, là một nội dung độc lập trong tham chiếu. | O80: 82 | P80: 80 | Q80: Hai người chấm thống nhất cao. A và B tương đương (82 vs 80). Ghi nhận lỗi: A: Bỏ ý Đảng và Nhà nước “tiếp tục đặt mục tiêu an toàn trước dịch bệnh”, là một nội dung độc lập trong tham chiếu. | B: Bỏ ý Đảng và Nhà nước “tiếp tục đặt mục tiêu an toàn trước dịch bệnh”, là một nội dung độc lập trong tham chiếu.
A81: 80 | B81: =Du_lieu_goc!C82 -> 河内市北慈廉郡古瑞坊居民杜氏川认为，阮富仲总书记在会上的讲话基于对当前面临的机遇和挑战的正确评估提出了新的发展方向。 | C81: =Du_lieu_goc!D82 -> Bà Đỗ Thị Xuyến, phường Cổ Nhuế, Quận Bắc Từ Liêm, Hà Nội, cho rằng những đường hướng mà Tổng Bí thư Nguyễn Phú Trọng nêu ra trong phát biểu khai mạc Hội nghị dựa trên những nhận định đúng về những thời cơ và thách thức trong tình hình hiện nay. | D81: Bà Đỗ Thị Xuyên, cư dân phường Cổ Nhuế, quận Bắc Từ Liêm, thành phố Hà Nội, nhận định rằng bài phát biểu của Tổng Bí thư Nguyễn Phú Trọng tại hội nghị đã đề ra những định hướng phát triển mới dựa trên đánh giá đúng đắn về những cơ hội và thách thức đang đối mặt. | E81: Bà Đỗ Thị Tray, cư dân Qu Thụy Fong, quận Bắc Từ Liêm, TP Hà Nội, tin rằng bài phát biểu của Tổng Bí thư Nguyễn Phú Trọng tại cuộc họp đã đề xuất hướng phát triển mới trên cơ sở đánh giá đúng cơ hội, thách thức hiện nay. | F81: Người 2 | G81: 78 | H81: 35 | I81: Người 3 | J81: 83 | K81: 75 | L81: Tên “Đỗ Thị Xuyến” bị viết thành “Đỗ Thị Xuyên”, làm sai tên riêng của người đưa ra nhận định. | M81: Sai tên người và địa bàn (“Đỗ Thị Tray”, “Qu Thụy Fong”), làm sai thực thể trung tâm của câu. | O81: 80 | P81: 55 | Q81: LỆCH LỚN 40 điểm giữa chấm chính và chấm chéo — cần rà lại. A vượt B rõ rệt (80 vs 55). Ghi nhận lỗi: A: Tên “Đỗ Thị Xuyến” bị viết thành “Đỗ Thị Xuyên”, làm sai tên riêng của người đưa ra nhận định. | B: Sai tên người và địa bàn (“Đỗ Thị Tray”, “Qu Thụy Fong”), làm sai thực thể trung tâm của câu. Điểm thấp — nên kiểm tra thủ công trước khi đưa vào tính tương quan.
A82: 81 | B82: =Du_lieu_goc!C83 -> 阮富仲在第十三届中央委员会第四次会议上发表的讲话给我留下了非常深刻的印象，我个人高度评价总书记对疫情之下社会经济发展情况所做的评估。 | C82: =Du_lieu_goc!D83 -> "Tôi rất tâm đắc với bài phát biểu của Tổng Bí thư Nguyễn Phú Trọng tại Hội nghị lần thứ 4, Ban chấp hành Trung ương khóa XIII， cá nhân tôi đánh giá cao những nhận định của Tổng Bí thư về tình hình kinh tế xã hội trước ảnh hưởng của đại dịch Covid- 19. | D82: Bài phát biểu của Tổng Bí thư Nguyễn Phú Trọng tại Hội nghị lần thứ tư Ban Chấp hành Trung ương khóa XIII đã để lại cho tôi ấn tượng sâu sắc, cá nhân tôi đánh giá cao những nhận định của Tổng Bí thư về tình hình phát triển kinh tế - xã hội trong bối cảnh dịch bệnh. | E82: Bài phát biểu của Nguyễn Phú Trọng tại kỳ họp thứ 4 Ban Chấp hành Trung ương khóa 13 để lại trong tôi ấn tượng rất sâu sắc. Cá nhân tôi đánh giá cao đánh giá của Tổng Bí thư về phát triển kinh tế - xã hội trong thời kỳ dịch bệnh. | F82: Người 2 | G82: 92 | H82: 84 | I82: Người 3 | J82: 85 | K82: 81 | O82: 88 | P82: 82 | Q82: Hai người chấm lệch nhẹ (7 điểm).
A83: 82 | B83: =Du_lieu_goc!C84 -> 作为一名党员，我个人对党和国家的主张政策和计划充满信心，并相信越南社会经济将及早稳定，恢复发展”。 | C83: =Du_lieu_goc!D84 -> Là một đảng viên, bản thân tôi bày tỏ sự tin tưởng trước những chủ trương, chính sách, kế hoạch của Đảng, Nhà nước trong thời gian tới và tin tưởng rằng tình hình kinh tế -xã hội sẽ sớm ổn định phục hồi và có sự phát triển". | D83: Với tư cách là một đảng viên, tôi tin tưởng vào các chủ trương, chính sách và kế hoạch của Đảng và Nhà nước, đồng thời tin rằng kinh tế - xã hội Việt Nam sẽ sớm ổn định và phục hồi phát triển. | E83: Với tư cách là một đảng viên, tôi tin tưởng vào các chủ trương, chính sách và kế hoạch của Đảng và Nhà nước, đồng thời tin rằng kinh tế - xã hội Việt Nam sẽ sớm ổn định và phục hồi phát triển. | F83: Người 2 | G83: 90 | H83: 90 | I83: Người 3 | J83: 84 | K83: 87 | O83: 87 | P83: 88 | Q83: Hai người chấm lệch nhẹ (6 điểm). A và B tương đương (87 vs 88).
A84: 83 | B84: =Du_lieu_goc!C85 -> 所以我认为，在这波疫情之后，我们可以拟定更多方案。 | C84: =Du_lieu_goc!D85 -> Vì thế tôi nghĩ là tính dự báo sau đợt này chúng ta có thể xây dựng được nhiều kịch bản và các kịch bản đó sẽ không bị bất ngờ như sự bùng phát vừa rồi đã diễn ra. | D84: Vì vậy, tôi cho rằng sau đợt dịch này, chúng ta có thể đề ra nhiều phương án hơn. | E84: Vì vậy tôi nghĩ rằng sau làn sóng dịch bệnh này, chúng ta có thể xây dựng thêm nhiều kế hoạch hơn. | F84: Người 2 | G84: 70 | H84: 72 | I84: Người 3 | J84: 85 | K84: 87 | L84: Tham chiếu còn có ý các kịch bản sau này “sẽ không bị bất ngờ như đợt bùng phát vừa rồi”; bản dịch bỏ toàn bộ ý này. | M84: Tham chiếu còn có ý các kịch bản sau này “sẽ không bị bất ngờ như đợt bùng phát vừa rồi”; bản dịch bỏ toàn bộ ý này. | O84: 78 | P84: 80 | Q84: LỆCH LỚN 15 điểm giữa chấm chính và chấm chéo — cần rà lại. A và B tương đương (78 vs 80). Ghi nhận lỗi: A: Tham chiếu còn có ý các kịch bản sau này “sẽ không bị bất ngờ như đợt bùng phát vừa rồi”; bản dịch bỏ toàn bộ ý này. | B: Tham chiếu còn có ý các kịch bản sau này “sẽ không bị bất ngờ như đợt bùng phát vừa rồi”; bản dịch bỏ toàn bộ ý này.
A85: 84 | B85: =Du_lieu_goc!C86 -> 基于对可能出现的各种情况的评估和分析，特别是对世界和越南疫情演变的研判，本次会议明确提出了新形势下防疫和恢复经济社会发展的主张和观点，旨在实现2021年经济社会发展目标。 | C85: =Du_lieu_goc!D86 -> Trên cơ sở phân tích, dự báo các khả năng có thể xảy ra, nhất là tình hình dịch bệnh trên thế giới và ở Việt Nam trong thời gian tới, Hội nghị Trung ương lần này xác định rõ quan điểm, chủ trương về phòng, chống dịch bệnh và phục hồi, phát triển kinh tế - xã hội trong tình hình mới nhằm hoàn thành chỉ tiêu phát triển kinh tế xã hội năm 2021. | D85: Dựa trên việc đánh giá và phân tích các tình huống có thể xảy ra, đặc biệt là nhận định về diễn biến dịch bệnh trên thế giới và tại Việt Nam, hội nghị đã đưa ra những chủ trương và quan điểm về công tác phòng chống dịch và phục hồi phát triển kinh tế - xã hội trong bối cảnh mới, nhằm thực hiện mục tiêu phát triển kinh tế - xã hội năm 2021. | E85: Trên cơ sở đánh giá, phân tích nhiều tình huống có thể xảy ra, đặc biệt là nghiên cứu, nhận định diễn biến dịch bệnh trên thế giới và Việt Nam, kỳ họp lần này đề xuất rõ ràng các ý tưởng, quan điểm về phòng chống dịch bệnh và khôi phục phát triển kinh tế, xã hội trong tình hình mới, hướng tới đạt được các mục tiêu phát triển kinh tế, xã hội năm 2021. | F85: Người 2 | G85: 82 | H85: 75 | I85: Người 3 | J85: 85 | K85: 87 | M85: “Chủ trương” bị hạ thành “ý tưởng”, đồng thời phần dự báo diễn biến dịch bị diễn đạt mờ hơn, làm giảm độ chính xác của định hướng hội nghị. | O85: 84 | P85: 81 | Q85: Hai người chấm lệch nhẹ (12 điểm). A và B tương đương (84 vs 81). Ghi nhận lỗi: B: “Chủ trương” bị hạ thành “ý tưởng”, đồng thời phần dự báo diễn biến dịch bị diễn đạt mờ hơn, làm giảm độ chính xác của định hướng hội nghị.
A86: 85 | B86: =Du_lieu_goc!C87 -> 此外，会议还提出了总体、基本和重要目标以及方向、主张、政策、任务、方案和2022年的具体实施方案和路线图，均符合实际，具有较高可行性，为从现在到2021年底和2022年全年集中领导和指导打下前提。 | C86: =Du_lieu_goc!D87 -> Hội nghị cũng đề ra mục tiêu tổng quát, các chỉ tiêu cơ bản, quan trọng nhất; các định hướng, chủ trương, chính sách, nhiệm vụ, giải pháp và kế hoạch, lộ trình triển khai thực hiện cụ thể cho năm 2022, bảo đảm sát với thực tiễn, có tính khả thi cao để tập trung lãnh đạo, chỉ đạo thực hiện từ nay đến cuối năm 2021 và trong cả năm 2022. | D86: Ngoài ra, hội nghị còn đề ra các mục tiêu tổng quát, cơ bản và quan trọng cùng với phương hướng, chủ trương, chính sách, nhiệm vụ, kế hoạch và lộ trình thực hiện cụ thể cho năm 2022, đều phù hợp với thực tế và có tính khả thi cao, tạo tiền đề cho việc tập trung lãnh đạo, chỉ đạo từ nay đến cuối năm 2021 và cả năm 2022. | E86: Ngoài ra, kỳ họp cũng đề xuất các mục tiêu tổng thể, cơ bản, quan trọng cũng như các phương hướng, đề xuất, chính sách, nhiệm vụ, kế hoạch và kế hoạch, lộ trình thực hiện cụ thể cho năm 2022 đều có tính thực tế và khả thi cao, làm tiền đề cho sự lãnh đạo, chỉ đạo tập trung từ nay đến cuối năm 2021 và trong suốt năm 2022. | F86: Người 2 | G86: 82 | H86: 70 | I86: Người 3 | J86: 94 | K86: 94 | L86: Bỏ thành phần “giải pháp” trong chuỗi định hướng–chủ trương–chính sách–nhiệm vụ–giải pháp–kế hoạch của tham chiếu. | M86: “Chủ trương” bị đổi thành “đề xuất” và chuỗi “giải pháp, kế hoạch” bị lặp/mất phân biệt. | O86: 88 | P86: 82 | Q86: LỆCH LỚN 24 điểm giữa chấm chính và chấm chéo — cần rà lại. Ghi nhận lỗi: A: Bỏ thành phần “giải pháp” trong chuỗi định hướng–chủ trương–chính sách–nhiệm vụ–giải pháp–kế hoạch của tham chiếu. | B: “Chủ trương” bị đổi thành “đề xuất” và chuỗi “giải pháp, kế hoạch” bị lặp/mất phân biệt.
A87: 86 | B87: =Du_lieu_goc!C88 -> 中央会议传递的正确信息体现了党意民心和在新形势下建设和发展国家的决心。 | C87: =Du_lieu_goc!D88 -> Những thông điệp đúng đắn từ Hội nghị Trung ương lần thể hiện ý Đảng, lòng dân, quyết tâm vì mục tiêu xây dựng và phát triển đất nước trong tình hình mới. | D87: Thông điệp chính xác được truyền tải từ hội nghị trung ương thể hiện sự đồng lòng của Đảng và nhân dân, cùng quyết tâm xây dựng và phát triển đất nước trong bối cảnh mới. | E87: Thông điệp đúng đắn của Trung ương Đảng thể hiện ý chí của Đảng và quyết tâm của nhân dân xây dựng và phát triển đất nước trong tình hình mới. | F87: Người 2 | G87: 86 | H87: 70 | I87: Người 3 | J87: 87 | K87: 92 | M87: “Ý Đảng, lòng dân” bị đổi thành “ý chí của Đảng và quyết tâm của nhân dân”, làm thay đổi quan hệ và sắc thái của hai thành tố. | O87: 86 | P87: 81 | Q87: LỆCH LỚN 22 điểm giữa chấm chính và chấm chéo — cần rà lại. Ghi nhận lỗi: B: “Ý Đảng, lòng dân” bị đổi thành “ý chí của Đảng và quyết tâm của nhân dân”, làm thay đổi quan hệ và sắc thái của hai thành tố.
A88: 87 | B88: =Du_lieu_goc!C89 -> 越南从“零新冠”目标转向适应、与疫情安全共处目标，为开放、逐步恢复经济创造条件。 | C88: =Du_lieu_goc!D89 -> Theo đó, chuyển mục tiêu “không ca mắc” (Zero Covid) sang mục tiêu thích ứng và chung sống an toàn với dịch bệnh, tạo điều kiện mở cửa và từng bước khôi phục hoạt động kinh tế. | D88: Việt Nam chuyển đổi từ mục tiêu "không COVID" sang mục tiêu thích ứng, sống an toàn với dịch bệnh, tạo điều kiện mở cửa, phục hồi kinh tế dần dần. | E88: Việt Nam đã chuyển từ mục tiêu “không có Covid-19” sang mục tiêu thích ứng và chung sống an toàn với dịch bệnh, tạo điều kiện mở cửa và từng bước vực dậy nền kinh tế. | F88: Người 2 | G88: 90 | H88: 76 | I88: Người 3 | J88: 83 | K88: 83 | M88: Bản dịch thêm “đã chuyển”, làm quá trình chuyển mục tiêu mang nghĩa đã hoàn tất so với tham chiếu. | O88: 86 | P88: 80 | Q88: Hai người chấm lệch nhẹ (7 điểm). Ghi nhận lỗi: B: Bản dịch thêm “đã chuyển”, làm quá trình chuyển mục tiêu mang nghĩa đã hoàn tất so với tham chiếu.
A89: 88 | B89: =Du_lieu_goc!C90 -> 安全适应，为随时开放、恢复经济做准备 | C89: =Du_lieu_goc!D90 -> Thích ứng an toàn, sẵn sàng mở cửa và khôi phục hoạt động kinh tế | D89: Chuẩn bị sẵn sàng để mở cửa và phục hồi kinh tế bất cứ lúc nào. | E89: Thích ứng an toàn và chuẩn bị mở cửa, phục hồi nền kinh tế bất cứ lúc nào | F89: Người 2 | G89: 70 | H89: 90 | I89: Người 3 | J89: 81 | K89: 95 | L89: Bỏ mất ý “thích ứng an toàn”, một thành phần chính của tham chiếu. | O89: 76 | P89: 92 | Q89: Hai người chấm lệch nhẹ (11 điểm). B vượt A rõ rệt (92 vs 76). Ghi nhận lỗi: A: Bỏ mất ý “thích ứng an toàn”, một thành phần chính của tham chiếu.
A90: 89 | B90: =Du_lieu_goc!C91 -> 越南卫生部卫生环境管理局局长阮氏莲香表示，安全适应意味着不追求零新增目标，而允许社区存在一定数量的病例，但须保障人民生命安全，继续发展经济社会及人民日常活动。 | C90: =Du_lieu_goc!D91 -> Theo Phó Giáo sư, Tiến sỹ Nguyễn Thị Liên Hương, Cục trưởng Cục Quản lý môi trường y tế - Bộ Y tế, thích ứng an toàn có nghĩa là không theo đuổi mục tiêu không có ca mắc Covid-19, mà chấp nhận có số ca mắc nhất định trong cộng đồng, nhưng phải đảm bảo an toàn tính mạng người dân và tiếp tục các hoạt động phát triển kinh tế xã hội, hoạt động sinh hoạt của người dân. | D90: Bà Nguyễn Thị Liên Hương, Cục trưởng Cục Quản lý Môi trường Y tế, Bộ Y tế Việt Nam, cho biết thích ứng an toàn có nghĩa là không theo đuổi mục tiêu không có ca nhiễm mới, mà cho phép cộng đồng có một số lượng ca bệnh nhất định, nhưng phải đảm bảo an toàn tính mạng cho người dân, tiếp tục phát triển kinh tế xã hội và các hoạt động thường nhật của người dân. | E90: Bà Nguyễn Thị Liên Hương, Cục trưởng Cục Quản lý Y tế và Môi trường, Bộ Y tế Việt Nam, cho rằng thích ứng an toàn có nghĩa là không theo đuổi mục tiêu không có ca nhiễm mới mà cho phép một số ca nhiễm nhất định trong cộng đồng nhưng phải đảm bảo an toàn tính mạng người dân và tiếp tục phát triển kinh tế, xã hội và sinh hoạt của người dân. | F90: Người 2 | G90: 92 | H90: 82 | I90: Người 3 | J90: 85 | K90: 85 | M90: Tên đơn vị “Cục Quản lý môi trường y tế” bị đổi thành “Cục Quản lý Y tế và Môi trường”, làm sai tên cơ quan. | O90: 88 | P90: 84 | Q90: Hai người chấm lệch nhẹ (7 điểm). Ghi nhận lỗi: B: Tên đơn vị “Cục Quản lý môi trường y tế” bị đổi thành “Cục Quản lý Y tế và Môi trường”, làm sai tên cơ quan.
A91: 90 | B91: =Du_lieu_goc!C92 -> 检测速度要快、科学、合理。 | C91: =Du_lieu_goc!D92 -> Còn xét nghiệm là phải thần tốc, khoa học, hợp lý và hiệu quả. | D91: Tốc độ kiểm tra cần nhanh chóng, khoa học và hợp lý. | E91: Tốc độ phát hiện phải nhanh, khoa học và hợp lý. | F91: Người 2 | G91: 70 | H91: 62 | I91: Người 3 | J91: 63 | K91: 63 | L91: “Xét nghiệm” bị đổi thành “kiểm tra” và bỏ “hiệu quả”, làm giảm độ chính xác của hành động phòng dịch. | M91: “Xét nghiệm” bị đổi thành “phát hiện” và bỏ “hiệu quả”, làm sai loại hành động được yêu cầu. | O91: 66 | P91: 62 | Q91: Hai người chấm lệch nhẹ (7 điểm). Ghi nhận lỗi: A: “Xét nghiệm” bị đổi thành “kiểm tra” và bỏ “hiệu quả”, làm giảm độ chính xác của hành động phòng dịch. | B: “Xét nghiệm” bị đổi thành “phát hiện” và bỏ “hiệu quả”, làm sai loại hành động được yêu cầu.
A92: 91 | B92: =Du_lieu_goc!C93 -> 重新开放经济是迫切要求，但范明政要求慎重、有序开放并制定适合、有效的路线图，在各地逐步、灵活实施，确保开放与安全的平衡。 | C92: =Du_lieu_goc!D93 -> Khẳng định việc mở cửa trở lại nền kinh tế là yêu cầu cấp bách, song Thủ tướng đồng thời lưu ý việc mở cửa phải thận trọng, có kế hoạch, lộ trình phù hợp, hiệu quả, thực hiện từng bước và linh hoạt áp dụng cho từng địa phương, bảo đảm hài hòa giữa mở cửa và an toàn dịch bệnh. | D92: Việc mở cửa lại nền kinh tế là yêu cầu cấp thiết, nhưng Phạm Minh Chính yêu cầu mở cửa một cách thận trọng, có trật tự và xây dựng lộ trình phù hợp, hiệu quả, triển khai từng bước, linh hoạt tại các địa phương, đảm bảo cân bằng giữa mở cửa và an toàn. | E92: Mở cửa lại nền kinh tế là yêu cầu cấp bách, nhưng Fan Mingzheng yêu cầu mở cửa thận trọng, có trật tự và xây dựng lộ trình phù hợp, hiệu quả, có thể thực hiện từng bước, linh hoạt ở nhiều nơi để đảm bảo cân bằng giữa mở cửa và an ninh. | F92: Người 2 | G92: 90 | H92: 38 | M92: Sai tên Phạm Minh Chính; “an toàn” bị đổi thành “an ninh”, đồng thời “từng địa phương” bị khái quát thành “nhiều nơi”. | O92: 90 | P92: 38 | Q92: Chỉ có điểm chấm chính (chưa chấm chéo). A vượt B rõ rệt (90 vs 38). Ghi nhận lỗi: B: Sai tên Phạm Minh Chính; “an toàn” bị đổi thành “an ninh”, đồng thời “từng địa phương” bị khái quát thành “nhiều nơi”. Điểm thấp — nên kiểm tra thủ công trước khi đưa vào tính tương quan.
A93: 92 | B93: =Du_lieu_goc!C94 -> 随时开放、恢复经济活动 | C93: =Du_lieu_goc!D94 -> Sẵn sàng mở cửa, khôi phục hoạt động kinh tế | D93: Mở cửa mọi lúc, khôi phục hoạt động kinh tế | E93: Mở cửa và tiếp tục các hoạt động kinh tế bất cứ lúc nào | F93: Người 2 | G93: 62 | H93: 58 | L93: “Sẵn sàng mở cửa” bị đổi thành “mở cửa mọi lúc”, làm đổi nghĩa khả năng/sẵn sàng thành hành động liên tục. | M93: “Khôi phục hoạt động kinh tế” bị đổi thành “tiếp tục các hoạt động kinh tế”, làm đổi trạng thái trước–sau của hoạt động. | O93: 62 | P93: 58 | Q93: Chỉ có điểm chấm chính (chưa chấm chéo). Ghi nhận lỗi: A: “Sẵn sàng mở cửa” bị đổi thành “mở cửa mọi lúc”, làm đổi nghĩa khả năng/sẵn sàng thành hành động liên tục. | B: “Khôi phục hoạt động kinh tế” bị đổi thành “tiếp tục các hoạt động kinh tế”, làm đổi trạng thái trước–sau của hoạt động. Điểm thấp — nên kiểm tra thủ công trước khi đưa vào tính tương quan.
A94: 93 | B94: =Du_lieu_goc!C95 -> 越南已经并继续是外国投资者的目的地。 | C94: =Du_lieu_goc!D95 -> Việt Nam đã, đang và sẽ tiếp tục là điểm đến hàng đầu của các nhà đầu tư quốc tế | D94: Việt Nam đã và tiếp tục là điểm đến của các nhà đầu tư nước ngoài. | E94: Việt Nam đã và đang tiếp tục là điểm đến của các nhà đầu tư nước ngoài. | F94: Người 2 | G94: 78 | H94: 82 | L94: Bỏ “đang”, “sẽ tiếp tục” và “hàng đầu” so với tham chiếu, làm giảm thông tin thời và mức độ. | M94: Bỏ “sẽ tiếp tục” và “hàng đầu” so với tham chiếu, làm thiếu thông tin thời và mức độ. | O94: 78 | P94: 82 | Q94: Chỉ có điểm chấm chính (chưa chấm chéo). Ghi nhận lỗi: A: Bỏ “đang”, “sẽ tiếp tục” và “hàng đầu” so với tham chiếu, làm giảm thông tin thời và mức độ. | B: Bỏ “sẽ tiếp tục” và “hàng đầu” so với tham chiếu, làm thiếu thông tin thời và mức độ.
A95: 94 | B95: =Du_lieu_goc!C96 -> 建党整党一直是党的核心任务并具有至关重要的意义。 | C95: =Du_lieu_goc!D96 -> Việc xây dựng, chỉnh đốn Đảng luôn luôn là nhiệm vụ then chốt, đặc biệt quan trọng, có ý nghĩa sống còn đối với Đảng và chế độ. | D95: Việc xây dựng và chỉnh đốn Đảng luôn là nhiệm vụ cốt lõi và có ý nghĩa vô cùng quan trọng của Đảng. | E95: Xây dựng Đảng, củng cố Đảng luôn là nhiệm vụ cốt lõi của Đảng và có ý nghĩa sống còn. | F95: Người 2 | G95: 72 | H95: 76 | L95: Bỏ ý “có ý nghĩa sống còn đối với Đảng và chế độ”, nên thiếu một phần quan trọng của tham chiếu. | M95: Giữ được “sống còn” nhưng bỏ “đối với Đảng và chế độ”, đồng thời “chỉnh đốn” bị đổi thành “củng cố”. | O95: 72 | P95: 76 | Q95: Chỉ có điểm chấm chính (chưa chấm chéo). Ghi nhận lỗi: A: Bỏ ý “có ý nghĩa sống còn đối với Đảng và chế độ”, nên thiếu một phần quan trọng của tham chiếu. | B: Giữ được “sống còn” nhưng bỏ “đối với Đảng và chế độ”, đồng thời “chỉnh đốn” bị đổi thành “củng cố”.
A96: 95 | B96: =Du_lieu_goc!C97 -> 进而，正确评估情况和查明原因；明确每个目标、观点、指导思想、主张以及符合每个内容和问题的措施，特别是本任期内具有突破性的解决方案”。 | C96: =Du_lieu_goc!D97 -> Từ đó, đánh giá đúng tình hình và nguyên nhân; xác định rõ mục tiêu, quan điểm, tư tưởng chỉ đạo và những chủ trương, biện pháp phù hợp đối với từng nội dung, vấn đề, nhất là những giải pháp có tính đột phá trong nhiệm kỳ này”. | D96: Tiếp theo, đánh giá đúng tình hình và làm rõ nguyên nhân; xác định rõ từng mục tiêu, quan điểm, tư tưởng chỉ đạo, chủ trương cũng như các biện pháp phù hợp với từng nội dung và vấn đề, đặc biệt là các giải pháp đột phá trong nhiệm kỳ này. | E96: Sau đó, đánh giá đúng thực trạng và xác định nguyên nhân; làm rõ từng mục tiêu, quan điểm, tư tưởng chỉ đạo, chủ trương, biện pháp phù hợp với từng nội dung, vấn đề, đặc biệt là những giải pháp đột phá trong nhiệm kỳ này.” | F96: Người 2 | G96: 94 | H96: 92 | O96: 94 | P96: 92 | Q96: Chỉ có điểm chấm chính (chưa chấm chéo). A và B tương đương (94 vs 92).
A97: 96 | B97: =Du_lieu_goc!C98 -> 越共十二届四中全会决议准确抓住了问题，正确评估了现状，发挥了整个政治体系和全国人民的综合力量，配套、有效采取各项措施，斗争并防止、遏制堕落现象、“自我演变”和“自我转化”表现，巩固了人民对党的信心。 | C97: =Du_lieu_goc!D98 -> Nghị quyết Trung ương 4 (khóa XII) đã lựa chọn vấn đề, đánh giá đúng thực trạng, phát huy sức mạnh tổng hợp của cả hệ thống chính trị, của nhân dân thực hiện đồng bộ các giải pháp để đấu tranh ngăn chặn, đẩy lùi sự suy thoái, "tự diễn biến", "tự chuyển hoá" có hiệu quả, củng cố niềm tin của nhân dân đối với Đảng. | D97: Nghị quyết Hội nghị Trung ương 4 khóa XII của Đảng Cộng sản Việt Nam đã nắm bắt chính xác vấn đề, đánh giá đúng thực trạng, phát huy sức mạnh tổng hợp của toàn hệ thống chính trị và nhân dân cả nước, đồng bộ, hiệu quả các biện pháp đấu tranh, ngăn chặn, đẩy lùi suy thoái tư tưởng chính trị, đạo đức, lối sống, "tự diễn biến", "tự chuyển hóa", củng cố niềm tin của nhân dân vào Đảng. | E97: Nghị quyết Hội nghị toàn thể lần thứ IV Ban Chấp hành Trung ương Đảng Cộng sản Việt Nam khóa XII đã quán triệt đúng vấn đề, đánh giá đúng tình hình hiện nay, phát huy sức mạnh toàn diện của cả hệ thống chính trị và nhân dân cả nước, phối hợp và triển khai có hiệu quả các giải pháp đấu tranh, ngăn chặn, kiềm chế hiện tượng thoái hóa, “tự diễn biến”, “tự chuyển hóa”, củng cố niềm tin của nhân dân vào Đảng. | F97: Người 2 | G97: 82 | H97: 80 | O97: 82 | P97: 80 | Q97: Chỉ có điểm chấm chính (chưa chấm chéo). A và B tương đương (82 vs 80).
A98: 97 | B98: =Du_lieu_goc!C99 -> 胡志明国家政治学院党建研究院前院长阮明俊评价称：“批评工作提升到新的高点，即对敏感问题、具体问题、明显表现进行批评。 | C98: =Du_lieu_goc!D99 -> Phó Giáo sư, Tiến sỹ Nguyễn Minh Tuấn, nguyên Viện trưởng Viện Xây dựng Đảng, Học viện Chính trị Quốc gia Hồ Chí Minh, đánh giá: “Phê bình đã ở mức cao hơn, tức là phê bình việc rất nhạy cảm. | D98: Nguyên viện trưởng Viện Xây dựng Đảng, Học viện Chính trị Quốc gia Hồ Chí Minh, ông Nguyễn Minh Tuấn nhận định: "Công tác phê bình đã nâng lên một tầm cao mới, đó là phê bình những vấn đề nhạy cảm, những vấn đề cụ thể, những biểu hiện rõ ràng." | E98: Nguyễn Minh Tuân, nguyên Viện trưởng Viện Nghiên cứu Xây dựng Đảng, Viện Khoa học Chính trị Quốc gia Hồ Chí Minh, nhận xét: “Công tác phê bình đã được nâng lên một tầm cao mới, đó là phê phán những vấn đề nhạy cảm, những vấn đề cụ thể, biểu hiện rõ ràng. | F98: Người 2 | G98: 95 | H98: 35 | M98: Sai tên Nguyễn Minh Tuấn và tên đơn vị công tác, nên toàn bộ nhận định bị gán cho sai thực thể. | O98: 95 | P98: 35 | Q98: Chỉ có điểm chấm chính (chưa chấm chéo). A vượt B rõ rệt (95 vs 35). Ghi nhận lỗi: B: Sai tên Nguyễn Minh Tuấn và tên đơn vị công tác, nên toàn bộ nhận định bị gán cho sai thực thể. Điểm thấp — nên kiểm tra thủ công trước khi đưa vào tính tương quan.
A99: 98 | B99: =Du_lieu_goc!C100 -> 越共十二届四中全会决议完善了解决党建工作紧迫问题所需的机制。 | C99: =Du_lieu_goc!D100 -> Với Nghị quyết Trung ương 4 (khóa XII), những vấn đề cấp bách của công tác xây dựng Đảng được hoàn thiện thể chế. | D99: Nghị quyết Hội nghị Trung ương 4 khóa XII Đảng Cộng sản Việt Nam đã hoàn thiện cơ chế cần thiết để giải quyết các vấn đề cấp bách trong công tác xây dựng Đảng. | E99: Nghị quyết Hội nghị toàn thể lần thứ 4 Ban Chấp hành Trung ương Đảng Cộng sản Việt Nam khóa 12 đã hoàn thiện các cơ chế cần thiết để giải quyết những vấn đề bức xúc trong công tác xây dựng Đảng. | F99: Người 2 | G99: 90 | H99: 85 | O99: 90 | P99: 85 | Q99: Chỉ có điểm chấm chính (chưa chấm chéo).
A100: 99 | B100: =Du_lieu_goc!C101 -> 此前，没有一次中央全体会议曾通过那么多关于干部工作的规定和流程。 | C100: =Du_lieu_goc!D101 -> Chưa có nhiệm kỳ nào Trung ương lại ban hành mới nhiều quy định, quy trình trong công tác cán bộ. | D100: Trước đây, chưa từng có một kỳ họp toàn thể trung ương nào thông qua nhiều quy định và quy trình về công tác cán bộ đến vậy. | E100: Trước đây, chưa có hội nghị toàn thể trung ương nào thông qua nhiều quy định, thủ tục về công tác cán bộ như vậy. | F100: Người 2 | G100: 60 | H100: 58 | L100: Tham chiếu nói “chưa có nhiệm kỳ nào”, nhưng bản dịch đổi thành “chưa có kỳ họp toàn thể nào”, làm sai phạm vi thời gian/sự kiện. | M100: Tham chiếu nói “chưa có nhiệm kỳ nào”, nhưng bản dịch đổi thành “chưa có hội nghị toàn thể trung ương nào”, làm sai phạm vi thời gian/sự kiện. | O100: 60 | P100: 58 | Q100: Chỉ có điểm chấm chính (chưa chấm chéo). A và B tương đương (60 vs 58). Ghi nhận lỗi: A: Tham chiếu nói “chưa có nhiệm kỳ nào”, nhưng bản dịch đổi thành “chưa có kỳ họp toàn thể nào”, làm sai phạm vi thời gian/sự kiện. | B: Tham chiếu nói “chưa có nhiệm kỳ nào”, nhưng bản dịch đổi thành “chưa có hội nghị toàn thể trung ương nào”, làm sai phạm vi thời gian/sự kiện. Điểm thấp — nên kiểm tra thủ công trước khi đưa vào tính tương quan.
...
